[
    {
        "identifier": "66970229000167-Americana-SP-CLARO-Pessoa Física",
        "cidade": "Americana",
        "uf": "SP",
        "latitude": -22.73736,
        "longitude": -47.333119,
        "empresa": "CLARO",
        "cnpj": 66970229000167,
        "data-dados": "2021-07",
        "pf-ou-pj": "Pessoa Física",
        "info-tecnologia": [
            {
                "tecnologia": "HFC",
                "tipo-de-Produto": "INTERNET",
                "meio-de-acesso": "Cabo Coaxial",
                "quantidade-acesso": 40303
            }
        ]
    },
    {
        "identifier": "66970229000167-Amparo-SP-CLARO-Pessoa Física",
        "cidade": "Amparo",
        "uf": "SP",
        "latitude": -22.70879,
        "longitude": -46.772022,
        "empresa": "CLARO",
        "cnpj": 66970229000167,
        "data-dados": "2021-07",
        "pf-ou-pj": "Pessoa Física",
        "info-tecnologia": [
            {
                "tecnologia": "FTTH",
                "tipo-de-Produto": "INTERNET",
                "meio-de-acesso": "Fibra",
                "quantidade-acesso": 3224
            }
        ]
    },
    {
        "identifier": "66970229000167-Andradina-SP-CLARO-Pessoa Física",
        "cidade": "Andradina",
        "uf": "SP",
        "latitude": -20.894761,
        "longitude": -51.378568,
        "empresa": "CLARO",
        "cnpj": 66970229000167,
        "data-dados": "2021-07",
        "pf-ou-pj": "Pessoa Física",
        "info-tecnologia": [
            {
                "tecnologia": "FTTH",
                "tipo-de-Produto": "INTERNET",
                "meio-de-acesso": "Fibra",
                "quantidade-acesso": 210
            }
        ]
    },
    {
        "identifier": "66970229000167-Aparecida-SP-CLARO-Pessoa Física",
        "cidade": "Aparecida",
        "uf": "SP",
        "latitude": -22.849509,
        "longitude": -45.232496,
        "empresa": "CLARO",
        "cnpj": 66970229000167,
        "data-dados": "2021-07",
        "pf-ou-pj": "Pessoa Física",
        "info-tecnologia": [
            {
                "tecnologia": "HFC",
                "tipo-de-Produto": "INTERNET",
                "meio-de-acesso": "Cabo Coaxial",
                "quantidade-acesso": 4118
            }
        ]
    },
    {
        "identifier": "66970229000167-Araraquara-SP-CLARO-Pessoa Física",
        "cidade": "Araraquara",
        "uf": "SP",
        "latitude": -21.784511,
        "longitude": -48.178014,
        "empresa": "CLARO",
        "cnpj": 66970229000167,
        "data-dados": "2021-07",
        "pf-ou-pj": "Pessoa Física",
        "info-tecnologia": [
            {
                "tecnologia": "HFC",
                "tipo-de-Produto": "INTERNET",
                "meio-de-acesso": "Cabo Coaxial",
                "quantidade-acesso": 30440
            }
        ]
    },
    {
        "identifier": "66970229000167-Araras-SP-CLARO-Pessoa Física",
        "cidade": "Araras",
        "uf": "SP",
        "latitude": -22.357238,
        "longitude": -47.384235,
        "empresa": "CLARO",
        "cnpj": 66970229000167,
        "data-dados": "2021-07",
        "pf-ou-pj": "Pessoa Física",
        "info-tecnologia": [
            {
                "tecnologia": "HFC",
                "tipo-de-Produto": "INTERNET",
                "meio-de-acesso": "Cabo Coaxial",
                "quantidade-acesso": 13562
            }
        ]
    },
    {
        "identifier": "66970229000167-Araçatuba-SP-CLARO-Pessoa Física",
        "cidade": "Araçatuba",
        "uf": "SP",
        "latitude": -21.207648,
        "longitude": -50.440106,
        "empresa": "CLARO",
        "cnpj": 66970229000167,
        "data-dados": "2021-07",
        "pf-ou-pj": "Pessoa Física",
        "info-tecnologia": [
            {
                "tecnologia": "HFC",
                "tipo-de-Produto": "INTERNET",
                "meio-de-acesso": "Cabo Coaxial",
                "quantidade-acesso": 24008
            }
        ]
    },
    {
        "identifier": "66970229000167-Artur Nogueira-SP-CLARO-Pessoa Física",
        "cidade": "Artur Nogueira",
        "uf": "SP",
        "latitude": -22.572737,
        "longitude": -47.172679,
        "empresa": "CLARO",
        "cnpj": 66970229000167,
        "data-dados": "2021-07",
        "pf-ou-pj": "Pessoa Física",
        "info-tecnologia": [
            {
                "tecnologia": "HFC",
                "tipo-de-Produto": "INTERNET",
                "meio-de-acesso": "Cabo Coaxial",
                "quantidade-acesso": 682
            }
        ]
    },
    {
        "identifier": "66970229000167-Arujá-SP-CLARO-Pessoa Física",
        "cidade": "Arujá",
        "uf": "SP",
        "latitude": -23.396476,
        "longitude": -46.319983,
        "empresa": "CLARO",
        "cnpj": 66970229000167,
        "data-dados": "2021-07",
        "pf-ou-pj": "Pessoa Física",
        "info-tecnologia": [
            {
                "tecnologia": "FTTH",
                "tipo-de-Produto": "INTERNET",
                "meio-de-acesso": "Fibra",
                "quantidade-acesso": 13355
            }
        ]
    },
    {
        "identifier": "66970229000167-Atibaia-SP-CLARO-Pessoa Física",
        "cidade": "Atibaia",
        "uf": "SP",
        "latitude": -23.117059,
        "longitude": -46.556262,
        "empresa": "CLARO",
        "cnpj": 66970229000167,
        "data-dados": "2021-07",
        "pf-ou-pj": "Pessoa Física",
        "info-tecnologia": [
            {
                "tecnologia": "HFC",
                "tipo-de-Produto": "INTERNET",
                "meio-de-acesso": "Cabo Coaxial",
                "quantidade-acesso": 12534
            }
        ]
    },
    {
        "identifier": "66970229000167-Barretos-SP-CLARO-Pessoa Física",
        "cidade": "Barretos",
        "uf": "SP",
        "latitude": -20.553146,
        "longitude": -48.569832,
        "empresa": "CLARO",
        "cnpj": 66970229000167,
        "data-dados": "2021-07",
        "pf-ou-pj": "Pessoa Física",
        "info-tecnologia": [
            {
                "tecnologia": "FTTH",
                "tipo-de-Produto": "INTERNET",
                "meio-de-acesso": "Fibra",
                "quantidade-acesso": 791
            }
        ]
    },
    {
        "identifier": "66970229000167-Barrinha-SP-CLARO-Pessoa Física",
        "cidade": "Barrinha",
        "uf": "SP",
        "latitude": -21.186374,
        "longitude": -48.163614,
        "empresa": "CLARO",
        "cnpj": 66970229000167,
        "data-dados": "2021-07",
        "pf-ou-pj": "Pessoa Física",
        "info-tecnologia": [
            {
                "tecnologia": "FTTH",
                "tipo-de-Produto": "INTERNET",
                "meio-de-acesso": "Fibra",
                "quantidade-acesso": 3009
            }
        ]
    },
    {
        "identifier": "66970229000167-Barueri-SP-CLARO-Pessoa Física",
        "cidade": "Barueri",
        "uf": "SP",
        "latitude": -23.505689,
        "longitude": -46.879042,
        "empresa": "CLARO",
        "cnpj": 66970229000167,
        "data-dados": "2021-07",
        "pf-ou-pj": "Pessoa Física",
        "info-tecnologia": [
            {
                "tecnologia": "HFC",
                "tipo-de-Produto": "INTERNET",
                "meio-de-acesso": "Cabo Coaxial",
                "quantidade-acesso": 59205
            }
        ]
    },
    {
        "identifier": "66970229000167-Batatais-SP-CLARO-Pessoa Física",
        "cidade": "Batatais",
        "uf": "SP",
        "latitude": -20.892867,
        "longitude": -47.592149,
        "empresa": "CLARO",
        "cnpj": 66970229000167,
        "data-dados": "2021-07",
        "pf-ou-pj": "Pessoa Física",
        "info-tecnologia": [
            {
                "tecnologia": "FTTH",
                "tipo-de-Produto": "INTERNET",
                "meio-de-acesso": "Fibra",
                "quantidade-acesso": 1321
            }
        ]
    },
    {
        "identifier": "66970229000167-Bauru-SP-CLARO-Pessoa Física",
        "cidade": "Bauru",
        "uf": "SP",
        "latitude": -22.324569,
        "longitude": -49.087142,
        "empresa": "CLARO",
        "cnpj": 66970229000167,
        "data-dados": "2021-07",
        "pf-ou-pj": "Pessoa Física",
        "info-tecnologia": [
            {
                "tecnologia": "HFC",
                "tipo-de-Produto": "INTERNET",
                "meio-de-acesso": "Cabo Coaxial",
                "quantidade-acesso": 48078
            }
        ]
    },
    {
        "identifier": "66970229000167-Bertioga-SP-CLARO-Pessoa Física",
        "cidade": "Bertioga",
        "uf": "SP",
        "latitude": -23.848568,
        "longitude": -46.139586,
        "empresa": "CLARO",
        "cnpj": 66970229000167,
        "data-dados": "2021-07",
        "pf-ou-pj": "Pessoa Física",
        "info-tecnologia": [
            {
                "tecnologia": "HFC",
                "tipo-de-Produto": "INTERNET",
                "meio-de-acesso": "Cabo Coaxial",
                "quantidade-acesso": 3710
            }
        ]
    },
    {
        "identifier": "66970229000167-Birigui-SP-CLARO-Pessoa Física",
        "cidade": "Birigui",
        "uf": "SP",
        "latitude": -21.291034,
        "longitude": -50.343162,
        "empresa": "CLARO",
        "cnpj": 66970229000167,
        "data-dados": "2021-07",
        "pf-ou-pj": "Pessoa Física",
        "info-tecnologia": [
            {
                "tecnologia": "FTTH",
                "tipo-de-Produto": "INTERNET",
                "meio-de-acesso": "Fibra",
                "quantidade-acesso": 191
            }
        ]
    },
    {
        "identifier": "66970229000167-Boituva-SP-CLARO-Pessoa Física",
        "cidade": "Boituva",
        "uf": "SP",
        "latitude": -23.285531,
        "longitude": -47.678574,
        "empresa": "CLARO",
        "cnpj": 66970229000167,
        "data-dados": "2021-07",
        "pf-ou-pj": "Pessoa Física",
        "info-tecnologia": [
            {
                "tecnologia": "FTTH",
                "tipo-de-Produto": "INTERNET",
                "meio-de-acesso": "Fibra",
                "quantidade-acesso": 4261
            }
        ]
    },
    {
        "identifier": "66970229000167-Botucatu-SP-CLARO-Pessoa Física",
        "cidade": "Botucatu",
        "uf": "SP",
        "latitude": -22.883697,
        "longitude": -48.443706,
        "empresa": "CLARO",
        "cnpj": 66970229000167,
        "data-dados": "2021-07",
        "pf-ou-pj": "Pessoa Física",
        "info-tecnologia": [
            {
                "tecnologia": "HFC",
                "tipo-de-Produto": "INTERNET",
                "meio-de-acesso": "Cabo Coaxial",
                "quantidade-acesso": 11291
            }
        ]
    },
    {
        "identifier": "66970229000167-Bragança Paulista-SP-CLARO-Pessoa Física",
        "cidade": "Bragança Paulista",
        "uf": "SP",
        "latitude": -22.952681,
        "longitude": -46.54188,
        "empresa": "CLARO",
        "cnpj": 66970229000167,
        "data-dados": "2021-07",
        "pf-ou-pj": "Pessoa Física",
        "info-tecnologia": [
            {
                "tecnologia": "HFC",
                "tipo-de-Produto": "INTERNET",
                "meio-de-acesso": "Cabo Coaxial",
                "quantidade-acesso": 23846
            }
        ]
    },
    {
        "identifier": "66970229000167-Cachoeira Paulista-SP-CLARO-Pessoa Física",
        "cidade": "Cachoeira Paulista",
        "uf": "SP",
        "latitude": -22.666498,
        "longitude": -45.015384,
        "empresa": "CLARO",
        "cnpj": 66970229000167,
        "data-dados": "2021-07",
        "pf-ou-pj": "Pessoa Física",
        "info-tecnologia": [
            {
                "tecnologia": "HFC",
                "tipo-de-Produto": "INTERNET",
                "meio-de-acesso": "Cabo Coaxial",
                "quantidade-acesso": 3477
            }
        ]
    },
    {
        "identifier": "66970229000167-Caieiras-SP-CLARO-Pessoa Física",
        "cidade": "Caieiras",
        "uf": "SP",
        "latitude": -23.360729,
        "longitude": -46.73974,
        "empresa": "CLARO",
        "cnpj": 66970229000167,
        "data-dados": "2021-07",
        "pf-ou-pj": "Pessoa Física",
        "info-tecnologia": [
            {
                "tecnologia": "FTTH",
                "tipo-de-Produto": "INTERNET",
                "meio-de-acesso": "Fibra",
                "quantidade-acesso": 5538
            }
        ]
    },
    {
        "identifier": "66970229000167-Campinas-SP-CLARO-Pessoa Física",
        "cidade": "Campinas",
        "uf": "SP",
        "latitude": -22.905346,
        "longitude": -47.06595,
        "empresa": "CLARO",
        "cnpj": 66970229000167,
        "data-dados": "2021-07",
        "pf-ou-pj": "Pessoa Física",
        "info-tecnologia": [
            {
                "tecnologia": "HFC",
                "tipo-de-Produto": "INTERNET",
                "meio-de-acesso": "Cabo Coaxial",
                "quantidade-acesso": 179357
            }
        ]
    },
    {
        "identifier": "66970229000167-Capivari-SP-CLARO-Pessoa Física",
        "cidade": "Capivari",
        "uf": "SP",
        "latitude": -22.995144,
        "longitude": -47.50715,
        "empresa": "CLARO",
        "cnpj": 66970229000167,
        "data-dados": "2021-07",
        "pf-ou-pj": "Pessoa Física",
        "info-tecnologia": [
            {
                "tecnologia": "HFC",
                "tipo-de-Produto": "INTERNET",
                "meio-de-acesso": "Cabo Coaxial",
                "quantidade-acesso": 3232
            }
        ]
    },
    {
        "identifier": "66970229000167-Caraguatatuba-SP-CLARO-Pessoa Física",
        "cidade": "Caraguatatuba",
        "uf": "SP",
        "latitude": -23.612535,
        "longitude": -45.412533,
        "empresa": "CLARO",
        "cnpj": 66970229000167,
        "data-dados": "2021-07",
        "pf-ou-pj": "Pessoa Física",
        "info-tecnologia": [
            {
                "tecnologia": "FTTH",
                "tipo-de-Produto": "INTERNET",
                "meio-de-acesso": "Fibra",
                "quantidade-acesso": 18766
            }
        ]
    },
    {
        "identifier": "66970229000167-Carapicuíba-SP-CLARO-Pessoa Física",
        "cidade": "Carapicuíba",
        "uf": "SP",
        "latitude": -23.523471,
        "longitude": -46.840676,
        "empresa": "CLARO",
        "cnpj": 66970229000167,
        "data-dados": "2021-07",
        "pf-ou-pj": "Pessoa Física",
        "info-tecnologia": [
            {
                "tecnologia": "HFC",
                "tipo-de-Produto": "INTERNET",
                "meio-de-acesso": "Cabo Coaxial",
                "quantidade-acesso": 19119
            }
        ]
    },
    {
        "identifier": "66970229000167-Catanduva-SP-CLARO-Pessoa Física",
        "cidade": "Catanduva",
        "uf": "SP",
        "latitude": -21.131381,
        "longitude": -48.977015,
        "empresa": "CLARO",
        "cnpj": 66970229000167,
        "data-dados": "2021-07",
        "pf-ou-pj": "Pessoa Física",
        "info-tecnologia": [
            {
                "tecnologia": "FTTH",
                "tipo-de-Produto": "INTERNET",
                "meio-de-acesso": "Fibra",
                "quantidade-acesso": 4411
            }
        ]
    },
    {
        "identifier": "66970229000167-Caçapava-SP-CLARO-Pessoa Física",
        "cidade": "Caçapava",
        "uf": "SP",
        "latitude": -23.099204,
        "longitude": -45.707645,
        "empresa": "CLARO",
        "cnpj": 66970229000167,
        "data-dados": "2021-07",
        "pf-ou-pj": "Pessoa Física",
        "info-tecnologia": [
            {
                "tecnologia": "HFC",
                "tipo-de-Produto": "INTERNET",
                "meio-de-acesso": "Cabo Coaxial",
                "quantidade-acesso": 8532
            }
        ]
    },
    {
        "identifier": "66970229000167-Cerquilho-SP-CLARO-Pessoa Física",
        "cidade": "Cerquilho",
        "uf": "SP",
        "latitude": -23.166487,
        "longitude": -47.745862,
        "empresa": "CLARO",
        "cnpj": 66970229000167,
        "data-dados": "2021-07",
        "pf-ou-pj": "Pessoa Física",
        "info-tecnologia": [
            {
                "tecnologia": "FTTH",
                "tipo-de-Produto": "INTERNET",
                "meio-de-acesso": "Fibra",
                "quantidade-acesso": 882
            }
        ]
    },
    {
        "identifier": "66970229000167-Cosmópolis-SP-CLARO-Pessoa Física",
        "cidade": "Cosmópolis",
        "uf": "SP",
        "latitude": -22.641906,
        "longitude": -47.192578,
        "empresa": "CLARO",
        "cnpj": 66970229000167,
        "data-dados": "2021-07",
        "pf-ou-pj": "Pessoa Física",
        "info-tecnologia": [
            {
                "tecnologia": "HFC",
                "tipo-de-Produto": "INTERNET",
                "meio-de-acesso": "Cabo Coaxial",
                "quantidade-acesso": 320
            }
        ]
    },
    {
        "identifier": "66970229000167-Cotia-SP-CLARO-Pessoa Física",
        "cidade": "Cotia",
        "uf": "SP",
        "latitude": -23.602177,
        "longitude": -46.91902,
        "empresa": "CLARO",
        "cnpj": 66970229000167,
        "data-dados": "2021-07",
        "pf-ou-pj": "Pessoa Física",
        "info-tecnologia": [
            {
                "tecnologia": "HFC",
                "tipo-de-Produto": "INTERNET",
                "meio-de-acesso": "Cabo Coaxial",
                "quantidade-acesso": 15443
            }
        ]
    },
    {
        "identifier": "66970229000167-Cravinhos-SP-CLARO-Pessoa Física",
        "cidade": "Cravinhos",
        "uf": "SP",
        "latitude": -21.337959,
        "longitude": -47.732427,
        "empresa": "CLARO",
        "cnpj": 66970229000167,
        "data-dados": "2021-07",
        "pf-ou-pj": "Pessoa Física",
        "info-tecnologia": [
            {
                "tecnologia": "FTTH",
                "tipo-de-Produto": "INTERNET",
                "meio-de-acesso": "Fibra",
                "quantidade-acesso": 1132
            }
        ]
    },
    {
        "identifier": "66970229000167-Cruzeiro-SP-CLARO-Pessoa Física",
        "cidade": "Cruzeiro",
        "uf": "SP",
        "latitude": -22.572764,
        "longitude": -44.96896,
        "empresa": "CLARO",
        "cnpj": 66970229000167,
        "data-dados": "2021-07",
        "pf-ou-pj": "Pessoa Física",
        "info-tecnologia": [
            {
                "tecnologia": "HFC",
                "tipo-de-Produto": "INTERNET",
                "meio-de-acesso": "Cabo Coaxial",
                "quantidade-acesso": 2157
            }
        ]
    },
    {
        "identifier": "66970229000167-Cubatão-SP-CLARO-Pessoa Física",
        "cidade": "Cubatão",
        "uf": "SP",
        "latitude": -23.891121,
        "longitude": -46.423968,
        "empresa": "CLARO",
        "cnpj": 66970229000167,
        "data-dados": "2021-07",
        "pf-ou-pj": "Pessoa Física",
        "info-tecnologia": [
            {
                "tecnologia": "HFC",
                "tipo-de-Produto": "INTERNET",
                "meio-de-acesso": "Cabo Coaxial",
                "quantidade-acesso": 6986
            }
        ]
    },
    {
        "identifier": "66970229000167-Descalvado-SP-CLARO-Pessoa Física",
        "cidade": "Descalvado",
        "uf": "SP",
        "latitude": -21.900211,
        "longitude": -47.618105,
        "empresa": "CLARO",
        "cnpj": 66970229000167,
        "data-dados": "2021-07",
        "pf-ou-pj": "Pessoa Física",
        "info-tecnologia": [
            {
                "tecnologia": "FTTH",
                "tipo-de-Produto": "INTERNET",
                "meio-de-acesso": "Fibra",
                "quantidade-acesso": 662
            }
        ]
    },
    {
        "identifier": "66970229000167-Diadema-SP-CLARO-Pessoa Física",
        "cidade": "Diadema",
        "uf": "SP",
        "latitude": -23.681347,
        "longitude": -46.62052,
        "empresa": "CLARO",
        "cnpj": 66970229000167,
        "data-dados": "2021-07",
        "pf-ou-pj": "Pessoa Física",
        "info-tecnologia": [
            {
                "tecnologia": "HFC",
                "tipo-de-Produto": "INTERNET",
                "meio-de-acesso": "Cabo Coaxial",
                "quantidade-acesso": 39650
            }
        ]
    },
    {
        "identifier": "66970229000167-Dracena-SP-CLARO-Pessoa Física",
        "cidade": "Dracena",
        "uf": "SP",
        "latitude": -21.484311,
        "longitude": -51.535034,
        "empresa": "CLARO",
        "cnpj": 66970229000167,
        "data-dados": "2021-07",
        "pf-ou-pj": "Pessoa Física",
        "info-tecnologia": [
            {
                "tecnologia": "FTTH",
                "tipo-de-Produto": "INTERNET",
                "meio-de-acesso": "Fibra",
                "quantidade-acesso": 1694
            }
        ]
    },
    {
        "identifier": "66970229000167-Elias Fausto-SP-CLARO-Pessoa Física",
        "cidade": "Elias Fausto",
        "uf": "SP",
        "latitude": -23.042822,
        "longitude": -47.368153,
        "empresa": "CLARO",
        "cnpj": 66970229000167,
        "data-dados": "2021-07",
        "pf-ou-pj": "Pessoa Física",
        "info-tecnologia": [
            {
                "tecnologia": "HFC",
                "tipo-de-Produto": "INTERNET",
                "meio-de-acesso": "Cabo Coaxial",
                "quantidade-acesso": 1109
            }
        ]
    },
    {
        "identifier": "66970229000167-Embu das Artes-SP-CLARO-Pessoa Física",
        "cidade": "Embu das Artes",
        "uf": "SP",
        "latitude": -23.643717,
        "longitude": -46.858776,
        "empresa": "CLARO",
        "cnpj": 66970229000167,
        "data-dados": "2021-07",
        "pf-ou-pj": "Pessoa Física",
        "info-tecnologia": [
            {
                "tecnologia": "HFC",
                "tipo-de-Produto": "INTERNET",
                "meio-de-acesso": "Cabo Coaxial",
                "quantidade-acesso": 14388
            }
        ]
    },
    {
        "identifier": "66970229000167-Espírito Santo do Pinhal-SP-CLARO-Pessoa Física",
        "cidade": "Espírito Santo do Pinhal",
        "uf": "SP",
        "latitude": -22.190871,
        "longitude": -46.74767,
        "empresa": "CLARO",
        "cnpj": 66970229000167,
        "data-dados": "2021-07",
        "pf-ou-pj": "Pessoa Física",
        "info-tecnologia": [
            {
                "tecnologia": "FTTH",
                "tipo-de-Produto": "INTERNET",
                "meio-de-acesso": "Fibra",
                "quantidade-acesso": 1041
            }
        ]
    },
    {
        "identifier": "66970229000167-Fernandópolis-SP-CLARO-Pessoa Física",
        "cidade": "Fernandópolis",
        "uf": "SP",
        "latitude": -20.280556,
        "longitude": -50.247115,
        "empresa": "CLARO",
        "cnpj": 66970229000167,
        "data-dados": "2021-07",
        "pf-ou-pj": "Pessoa Física",
        "info-tecnologia": [
            {
                "tecnologia": "FTTH",
                "tipo-de-Produto": "INTERNET",
                "meio-de-acesso": "Fibra",
                "quantidade-acesso": 1
            }
        ]
    },
    {
        "identifier": "66970229000167-Franca-SP-CLARO-Pessoa Física",
        "cidade": "Franca",
        "uf": "SP",
        "latitude": -20.53523,
        "longitude": -47.403861,
        "empresa": "CLARO",
        "cnpj": 66970229000167,
        "data-dados": "2021-07",
        "pf-ou-pj": "Pessoa Física",
        "info-tecnologia": [
            {
                "tecnologia": "HFC",
                "tipo-de-Produto": "INTERNET",
                "meio-de-acesso": "Cabo Coaxial",
                "quantidade-acesso": 39214
            }
        ]
    },
    {
        "identifier": "66970229000167-Guaratinguetá-SP-CLARO-Pessoa Física",
        "cidade": "Guaratinguetá",
        "uf": "SP",
        "latitude": -22.807534,
        "longitude": -45.193788,
        "empresa": "CLARO",
        "cnpj": 66970229000167,
        "data-dados": "2021-07",
        "pf-ou-pj": "Pessoa Física",
        "info-tecnologia": [
            {
                "tecnologia": "HFC",
                "tipo-de-Produto": "INTERNET",
                "meio-de-acesso": "Cabo Coaxial",
                "quantidade-acesso": 9964
            }
        ]
    },
    {
        "identifier": "66970229000167-Guarujá-SP-CLARO-Pessoa Física",
        "cidade": "Guarujá",
        "uf": "SP",
        "latitude": -23.988798,
        "longitude": -46.257959,
        "empresa": "CLARO",
        "cnpj": 66970229000167,
        "data-dados": "2021-07",
        "pf-ou-pj": "Pessoa Física",
        "info-tecnologia": [
            {
                "tecnologia": "HFC",
                "tipo-de-Produto": "INTERNET",
                "meio-de-acesso": "Cabo Coaxial",
                "quantidade-acesso": 36073
            }
        ]
    },
    {
        "identifier": "66970229000167-Guarulhos-SP-CLARO-Pessoa Física",
        "cidade": "Guarulhos",
        "uf": "SP",
        "latitude": -23.453758,
        "longitude": -46.533347,
        "empresa": "CLARO",
        "cnpj": 66970229000167,
        "data-dados": "2021-07",
        "pf-ou-pj": "Pessoa Física",
        "info-tecnologia": [
            {
                "tecnologia": "HFC",
                "tipo-de-Produto": "INTERNET",
                "meio-de-acesso": "Cabo Coaxial",
                "quantidade-acesso": 176592
            }
        ]
    },
    {
        "identifier": "66970229000167-Hortolândia-SP-CLARO-Pessoa Física",
        "cidade": "Hortolândia",
        "uf": "SP",
        "latitude": -22.852854,
        "longitude": -47.214259,
        "empresa": "CLARO",
        "cnpj": 66970229000167,
        "data-dados": "2021-07",
        "pf-ou-pj": "Pessoa Física",
        "info-tecnologia": [
            {
                "tecnologia": "HFC",
                "tipo-de-Produto": "INTERNET",
                "meio-de-acesso": "Cabo Coaxial",
                "quantidade-acesso": 6621
            }
        ]
    },
    {
        "identifier": "66970229000167-Indaiatuba-SP-CLARO-Pessoa Física",
        "cidade": "Indaiatuba",
        "uf": "SP",
        "latitude": -23.081591,
        "longitude": -47.210093,
        "empresa": "CLARO",
        "cnpj": 66970229000167,
        "data-dados": "2021-07",
        "pf-ou-pj": "Pessoa Física",
        "info-tecnologia": [
            {
                "tecnologia": "HFC",
                "tipo-de-Produto": "INTERNET",
                "meio-de-acesso": "Cabo Coaxial",
                "quantidade-acesso": 32865
            }
        ]
    },
    {
        "identifier": "66970229000167-Itanhaém-SP-CLARO-Pessoa Física",
        "cidade": "Itanhaém",
        "uf": "SP",
        "latitude": -24.173633,
        "longitude": -46.787986,
        "empresa": "CLARO",
        "cnpj": 66970229000167,
        "data-dados": "2021-07",
        "pf-ou-pj": "Pessoa Física",
        "info-tecnologia": [
            {
                "tecnologia": "FTTH",
                "tipo-de-Produto": "INTERNET",
                "meio-de-acesso": "Fibra",
                "quantidade-acesso": 10766
            }
        ]
    },
    {
        "identifier": "66970229000167-Itapecerica da Serra-SP-CLARO-Pessoa Física",
        "cidade": "Itapecerica da Serra",
        "uf": "SP",
        "latitude": -23.716135,
        "longitude": -46.857193,
        "empresa": "CLARO",
        "cnpj": 66970229000167,
        "data-dados": "2021-07",
        "pf-ou-pj": "Pessoa Física",
        "info-tecnologia": [
            {
                "tecnologia": "HFC",
                "tipo-de-Produto": "INTERNET",
                "meio-de-acesso": "Cabo Coaxial",
                "quantidade-acesso": 5880
            }
        ]
    },
    {
        "identifier": "66970229000167-Itapetininga-SP-CLARO-Pessoa Física",
        "cidade": "Itapetininga",
        "uf": "SP",
        "latitude": -23.588607,
        "longitude": -48.048326,
        "empresa": "CLARO",
        "cnpj": 66970229000167,
        "data-dados": "2021-07",
        "pf-ou-pj": "Pessoa Física",
        "info-tecnologia": [
            {
                "tecnologia": "HFC",
                "tipo-de-Produto": "INTERNET",
                "meio-de-acesso": "Cabo Coaxial",
                "quantidade-acesso": 13922
            }
        ]
    },
    {
        "identifier": "66970229000167-Itapevi-SP-CLARO-Pessoa Física",
        "cidade": "Itapevi",
        "uf": "SP",
        "latitude": -23.548774,
        "longitude": -46.932747,
        "empresa": "CLARO",
        "cnpj": 66970229000167,
        "data-dados": "2021-07",
        "pf-ou-pj": "Pessoa Física",
        "info-tecnologia": [
            {
                "tecnologia": "HFC",
                "tipo-de-Produto": "INTERNET",
                "meio-de-acesso": "Cabo Coaxial",
                "quantidade-acesso": 4169
            }
        ]
    },
    {
        "identifier": "66970229000167-Itapira-SP-CLARO-Pessoa Física",
        "cidade": "Itapira",
        "uf": "SP",
        "latitude": -22.435731,
        "longitude": -46.822434,
        "empresa": "CLARO",
        "cnpj": 66970229000167,
        "data-dados": "2021-07",
        "pf-ou-pj": "Pessoa Física",
        "info-tecnologia": [
            {
                "tecnologia": "FTTH",
                "tipo-de-Produto": "INTERNET",
                "meio-de-acesso": "Fibra",
                "quantidade-acesso": 2681
            }
        ]
    },
    {
        "identifier": "66970229000167-Itatiba-SP-CLARO-Pessoa Física",
        "cidade": "Itatiba",
        "uf": "SP",
        "latitude": -23.003497,
        "longitude": -46.846353,
        "empresa": "CLARO",
        "cnpj": 66970229000167,
        "data-dados": "2021-07",
        "pf-ou-pj": "Pessoa Física",
        "info-tecnologia": [
            {
                "tecnologia": "FTTH",
                "tipo-de-Produto": "INTERNET",
                "meio-de-acesso": "Fibra",
                "quantidade-acesso": 7787
            }
        ]
    },
    {
        "identifier": "66970229000167-Itu-SP-CLARO-Pessoa Física",
        "cidade": "Itu",
        "uf": "SP",
        "latitude": -23.254397,
        "longitude": -47.292688,
        "empresa": "CLARO",
        "cnpj": 66970229000167,
        "data-dados": "2021-07",
        "pf-ou-pj": "Pessoa Física",
        "info-tecnologia": [
            {
                "tecnologia": "HFC",
                "tipo-de-Produto": "INTERNET",
                "meio-de-acesso": "Cabo Coaxial",
                "quantidade-acesso": 24213
            }
        ]
    },
    {
        "identifier": "66970229000167-Itupeva-SP-CLARO-Pessoa Física",
        "cidade": "Itupeva",
        "uf": "SP",
        "latitude": -23.152635,
        "longitude": -47.059262,
        "empresa": "CLARO",
        "cnpj": 66970229000167,
        "data-dados": "2021-07",
        "pf-ou-pj": "Pessoa Física",
        "info-tecnologia": [
            {
                "tecnologia": "FTTH",
                "tipo-de-Produto": "INTERNET",
                "meio-de-acesso": "Fibra",
                "quantidade-acesso": 1347
            }
        ]
    },
    {
        "identifier": "66970229000167-Ituverava-SP-CLARO-Pessoa Física",
        "cidade": "Ituverava",
        "uf": "SP",
        "latitude": -20.335465,
        "longitude": -47.790207,
        "empresa": "CLARO",
        "cnpj": 66970229000167,
        "data-dados": "2021-07",
        "pf-ou-pj": "Pessoa Física",
        "info-tecnologia": [
            {
                "tecnologia": "FTTH",
                "tipo-de-Produto": "INTERNET",
                "meio-de-acesso": "Fibra",
                "quantidade-acesso": 27
            }
        ]
    },
    {
        "identifier": "66970229000167-Jacareí-SP-CLARO-Pessoa Física",
        "cidade": "Jacareí",
        "uf": "SP",
        "latitude": -23.29829,
        "longitude": -45.965814,
        "empresa": "CLARO",
        "cnpj": 66970229000167,
        "data-dados": "2021-07",
        "pf-ou-pj": "Pessoa Física",
        "info-tecnologia": [
            {
                "tecnologia": "HFC",
                "tipo-de-Produto": "INTERNET",
                "meio-de-acesso": "Cabo Coaxial",
                "quantidade-acesso": 16320
            }
        ]
    },
    {
        "identifier": "66970229000167-Jaguariúna-SP-CLARO-Pessoa Física",
        "cidade": "Jaguariúna",
        "uf": "SP",
        "latitude": -22.70374,
        "longitude": -46.985062,
        "empresa": "CLARO",
        "cnpj": 66970229000167,
        "data-dados": "2021-07",
        "pf-ou-pj": "Pessoa Física",
        "info-tecnologia": [
            {
                "tecnologia": "FTTH",
                "tipo-de-Produto": "INTERNET",
                "meio-de-acesso": "Fibra",
                "quantidade-acesso": 4633
            }
        ]
    },
    {
        "identifier": "66970229000167-Jales-SP-CLARO-Pessoa Física",
        "cidade": "Jales",
        "uf": "SP",
        "latitude": -20.267227,
        "longitude": -50.549442,
        "empresa": "CLARO",
        "cnpj": 66970229000167,
        "data-dados": "2021-07",
        "pf-ou-pj": "Pessoa Física",
        "info-tecnologia": [
            {
                "tecnologia": "FTTH",
                "tipo-de-Produto": "INTERNET",
                "meio-de-acesso": "Fibra",
                "quantidade-acesso": 348
            }
        ]
    },
    {
        "identifier": "66970229000167-Jandira-SP-CLARO-Pessoa Física",
        "cidade": "Jandira",
        "uf": "SP",
        "latitude": -23.527537,
        "longitude": -46.902314,
        "empresa": "CLARO",
        "cnpj": 66970229000167,
        "data-dados": "2021-07",
        "pf-ou-pj": "Pessoa Física",
        "info-tecnologia": [
            {
                "tecnologia": "HFC",
                "tipo-de-Produto": "INTERNET",
                "meio-de-acesso": "Cabo Coaxial",
                "quantidade-acesso": 5946
            }
        ]
    },
    {
        "identifier": "66970229000167-Jaú-SP-CLARO-Pessoa Física",
        "cidade": "Jaú",
        "uf": "SP",
        "latitude": -22.293585,
        "longitude": -48.559193,
        "empresa": "CLARO",
        "cnpj": 66970229000167,
        "data-dados": "2021-07",
        "pf-ou-pj": "Pessoa Física",
        "info-tecnologia": [
            {
                "tecnologia": "HFC",
                "tipo-de-Produto": "INTERNET",
                "meio-de-acesso": "Cabo Coaxial",
                "quantidade-acesso": 14820
            }
        ]
    },
    {
        "identifier": "66970229000167-Jundiaí-SP-CLARO-Pessoa Física",
        "cidade": "Jundiaí",
        "uf": "SP",
        "latitude": -23.185218,
        "longitude": -46.897358,
        "empresa": "CLARO",
        "cnpj": 66970229000167,
        "data-dados": "2021-07",
        "pf-ou-pj": "Pessoa Física",
        "info-tecnologia": [
            {
                "tecnologia": "HFC",
                "tipo-de-Produto": "INTERNET",
                "meio-de-acesso": "Cabo Coaxial",
                "quantidade-acesso": 70525
            }
        ]
    },
    {
        "identifier": "66970229000167-Limeira-SP-CLARO-Pessoa Física",
        "cidade": "Limeira",
        "uf": "SP",
        "latitude": -22.56605,
        "longitude": -47.396987,
        "empresa": "CLARO",
        "cnpj": 66970229000167,
        "data-dados": "2021-07",
        "pf-ou-pj": "Pessoa Física",
        "info-tecnologia": [
            {
                "tecnologia": "HFC",
                "tipo-de-Produto": "INTERNET",
                "meio-de-acesso": "Cabo Coaxial",
                "quantidade-acesso": 15291
            }
        ]
    },
    {
        "identifier": "66970229000167-Lins-SP-CLARO-Pessoa Física",
        "cidade": "Lins",
        "uf": "SP",
        "latitude": -21.67182,
        "longitude": -49.752555,
        "empresa": "CLARO",
        "cnpj": 66970229000167,
        "data-dados": "2021-07",
        "pf-ou-pj": "Pessoa Física",
        "info-tecnologia": [
            {
                "tecnologia": "FTTH",
                "tipo-de-Produto": "INTERNET",
                "meio-de-acesso": "Fibra",
                "quantidade-acesso": 424
            }
        ]
    },
    {
        "identifier": "66970229000167-Lorena-SP-CLARO-Pessoa Física",
        "cidade": "Lorena",
        "uf": "SP",
        "latitude": -22.73338,
        "longitude": -45.11968,
        "empresa": "CLARO",
        "cnpj": 66970229000167,
        "data-dados": "2021-07",
        "pf-ou-pj": "Pessoa Física",
        "info-tecnologia": [
            {
                "tecnologia": "HFC",
                "tipo-de-Produto": "INTERNET",
                "meio-de-acesso": "Cabo Coaxial",
                "quantidade-acesso": 7267
            }
        ]
    },
    {
        "identifier": "66970229000167-Louveira-SP-CLARO-Pessoa Física",
        "cidade": "Louveira",
        "uf": "SP",
        "latitude": -23.085572,
        "longitude": -46.948369,
        "empresa": "CLARO",
        "cnpj": 66970229000167,
        "data-dados": "2021-07",
        "pf-ou-pj": "Pessoa Física",
        "info-tecnologia": [
            {
                "tecnologia": "FTTH",
                "tipo-de-Produto": "INTERNET",
                "meio-de-acesso": "Fibra",
                "quantidade-acesso": 1841
            }
        ]
    },
    {
        "identifier": "66970229000167-Mairinque-SP-CLARO-Pessoa Física",
        "cidade": "Mairinque",
        "uf": "SP",
        "latitude": -23.539822,
        "longitude": -47.184995,
        "empresa": "CLARO",
        "cnpj": 66970229000167,
        "data-dados": "2021-07",
        "pf-ou-pj": "Pessoa Física",
        "info-tecnologia": [
            {
                "tecnologia": "FTTH",
                "tipo-de-Produto": "INTERNET",
                "meio-de-acesso": "Fibra",
                "quantidade-acesso": 1041
            }
        ]
    },
    {
        "identifier": "66970229000167-Marília-SP-CLARO-Pessoa Física",
        "cidade": "Marília",
        "uf": "SP",
        "latitude": -22.217108,
        "longitude": -49.95006,
        "empresa": "CLARO",
        "cnpj": 66970229000167,
        "data-dados": "2021-07",
        "pf-ou-pj": "Pessoa Física",
        "info-tecnologia": [
            {
                "tecnologia": "HFC",
                "tipo-de-Produto": "INTERNET",
                "meio-de-acesso": "Cabo Coaxial",
                "quantidade-acesso": 36191
            }
        ]
    },
    {
        "identifier": "66970229000167-Matão-SP-CLARO-Pessoa Física",
        "cidade": "Matão",
        "uf": "SP",
        "latitude": -21.602511,
        "longitude": -48.363968,
        "empresa": "CLARO",
        "cnpj": 66970229000167,
        "data-dados": "2021-07",
        "pf-ou-pj": "Pessoa Física",
        "info-tecnologia": [
            {
                "tecnologia": "FTTH",
                "tipo-de-Produto": "INTERNET",
                "meio-de-acesso": "Fibra",
                "quantidade-acesso": 454
            }
        ]
    },
    {
        "identifier": "66970229000167-Mauá-SP-CLARO-Pessoa Física",
        "cidade": "Mauá",
        "uf": "SP",
        "latitude": -23.66767,
        "longitude": -46.461263,
        "empresa": "CLARO",
        "cnpj": 66970229000167,
        "data-dados": "2021-07",
        "pf-ou-pj": "Pessoa Física",
        "info-tecnologia": [
            {
                "tecnologia": "HFC",
                "tipo-de-Produto": "INTERNET",
                "meio-de-acesso": "Cabo Coaxial",
                "quantidade-acesso": 32240
            }
        ]
    },
    {
        "identifier": "66970229000167-Mirassol-SP-CLARO-Pessoa Física",
        "cidade": "Mirassol",
        "uf": "SP",
        "latitude": -20.816874,
        "longitude": -49.52061,
        "empresa": "CLARO",
        "cnpj": 66970229000167,
        "data-dados": "2021-07",
        "pf-ou-pj": "Pessoa Física",
        "info-tecnologia": [
            {
                "tecnologia": "FTTH",
                "tipo-de-Produto": "INTERNET",
                "meio-de-acesso": "Fibra",
                "quantidade-acesso": 4839
            }
        ]
    },
    {
        "identifier": "66970229000167-Mococa-SP-CLARO-Pessoa Física",
        "cidade": "Mococa",
        "uf": "SP",
        "latitude": -21.464731,
        "longitude": -47.002405,
        "empresa": "CLARO",
        "cnpj": 66970229000167,
        "data-dados": "2021-07",
        "pf-ou-pj": "Pessoa Física",
        "info-tecnologia": [
            {
                "tecnologia": "FTTH",
                "tipo-de-Produto": "INTERNET",
                "meio-de-acesso": "Fibra",
                "quantidade-acesso": 1725
            }
        ]
    },
    {
        "identifier": "66970229000167-Mogi Guaçu-SP-CLARO-Pessoa Física",
        "cidade": "Mogi Guaçu",
        "uf": "SP",
        "latitude": -22.367453,
        "longitude": -46.9428,
        "empresa": "CLARO",
        "cnpj": 66970229000167,
        "data-dados": "2021-07",
        "pf-ou-pj": "Pessoa Física",
        "info-tecnologia": [
            {
                "tecnologia": "HFC",
                "tipo-de-Produto": "INTERNET",
                "meio-de-acesso": "Cabo Coaxial",
                "quantidade-acesso": 18603
            }
        ]
    },
    {
        "identifier": "66970229000167-Mogi Mirim-SP-CLARO-Pessoa Física",
        "cidade": "Mogi Mirim",
        "uf": "SP",
        "latitude": -22.431878,
        "longitude": -46.950514,
        "empresa": "CLARO",
        "cnpj": 66970229000167,
        "data-dados": "2021-07",
        "pf-ou-pj": "Pessoa Física",
        "info-tecnologia": [
            {
                "tecnologia": "HFC",
                "tipo-de-Produto": "INTERNET",
                "meio-de-acesso": "Cabo Coaxial",
                "quantidade-acesso": 11877
            }
        ]
    },
    {
        "identifier": "66970229000167-Mogi das Cruzes-SP-CLARO-Pessoa Física",
        "cidade": "Mogi das Cruzes",
        "uf": "SP",
        "latitude": -23.52082,
        "longitude": -46.18541,
        "empresa": "CLARO",
        "cnpj": 66970229000167,
        "data-dados": "2021-07",
        "pf-ou-pj": "Pessoa Física",
        "info-tecnologia": [
            {
                "tecnologia": "HFC",
                "tipo-de-Produto": "INTERNET",
                "meio-de-acesso": "Cabo Coaxial",
                "quantidade-acesso": 73735
            }
        ]
    },
    {
        "identifier": "66970229000167-Mongaguá-SP-CLARO-Pessoa Física",
        "cidade": "Mongaguá",
        "uf": "SP",
        "latitude": -24.080901,
        "longitude": -46.626526,
        "empresa": "CLARO",
        "cnpj": 66970229000167,
        "data-dados": "2021-07",
        "pf-ou-pj": "Pessoa Física",
        "info-tecnologia": [
            {
                "tecnologia": "FTTH",
                "tipo-de-Produto": "INTERNET",
                "meio-de-acesso": "Fibra",
                "quantidade-acesso": 13677
            }
        ]
    },
    {
        "identifier": "66970229000167-Monte Mor-SP-CLARO-Pessoa Física",
        "cidade": "Monte Mor",
        "uf": "SP",
        "latitude": -22.945043,
        "longitude": -47.312182,
        "empresa": "CLARO",
        "cnpj": 66970229000167,
        "data-dados": "2021-07",
        "pf-ou-pj": "Pessoa Física",
        "info-tecnologia": [
            {
                "tecnologia": "HFC",
                "tipo-de-Produto": "INTERNET",
                "meio-de-acesso": "Cabo Coaxial",
                "quantidade-acesso": 2203
            }
        ]
    },
    {
        "identifier": "66970229000167-Nova Odessa-SP-CLARO-Pessoa Física",
        "cidade": "Nova Odessa",
        "uf": "SP",
        "latitude": -22.783186,
        "longitude": -47.294059,
        "empresa": "CLARO",
        "cnpj": 66970229000167,
        "data-dados": "2021-07",
        "pf-ou-pj": "Pessoa Física",
        "info-tecnologia": [
            {
                "tecnologia": "HFC",
                "tipo-de-Produto": "INTERNET",
                "meio-de-acesso": "Cabo Coaxial",
                "quantidade-acesso": 2341
            }
        ]
    },
    {
        "identifier": "66970229000167-Orlândia-SP-CLARO-Pessoa Física",
        "cidade": "Orlândia",
        "uf": "SP",
        "latitude": -20.716925,
        "longitude": -47.885205,
        "empresa": "CLARO",
        "cnpj": 66970229000167,
        "data-dados": "2021-07",
        "pf-ou-pj": "Pessoa Física",
        "info-tecnologia": [
            {
                "tecnologia": "FTTH",
                "tipo-de-Produto": "INTERNET",
                "meio-de-acesso": "Fibra",
                "quantidade-acesso": 2353
            }
        ]
    },
    {
        "identifier": "66970229000167-Osasco-SP-CLARO-Pessoa Física",
        "cidade": "Osasco",
        "uf": "SP",
        "latitude": -23.53239,
        "longitude": -46.791555,
        "empresa": "CLARO",
        "cnpj": 66970229000167,
        "data-dados": "2021-07",
        "pf-ou-pj": "Pessoa Física",
        "info-tecnologia": [
            {
                "tecnologia": "HFC",
                "tipo-de-Produto": "INTERNET",
                "meio-de-acesso": "Cabo Coaxial",
                "quantidade-acesso": 113208
            }
        ]
    },
    {
        "identifier": "66970229000167-Paulínia-SP-CLARO-Pessoa Física",
        "cidade": "Paulínia",
        "uf": "SP",
        "latitude": -22.754178,
        "longitude": -47.148776,
        "empresa": "CLARO",
        "cnpj": 66970229000167,
        "data-dados": "2021-07",
        "pf-ou-pj": "Pessoa Física",
        "info-tecnologia": [
            {
                "tecnologia": "HFC",
                "tipo-de-Produto": "INTERNET",
                "meio-de-acesso": "Cabo Coaxial",
                "quantidade-acesso": 8317
            }
        ]
    },
    {
        "identifier": "66970229000167-Pedreira-SP-CLARO-Pessoa Física",
        "cidade": "Pedreira",
        "uf": "SP",
        "latitude": -22.741347,
        "longitude": -46.894846,
        "empresa": "CLARO",
        "cnpj": 66970229000167,
        "data-dados": "2021-07",
        "pf-ou-pj": "Pessoa Física",
        "info-tecnologia": [
            {
                "tecnologia": "FTTH",
                "tipo-de-Produto": "INTERNET",
                "meio-de-acesso": "Fibra",
                "quantidade-acesso": 1844
            }
        ]
    },
    {
        "identifier": "66970229000167-Penápolis-SP-CLARO-Pessoa Física",
        "cidade": "Penápolis",
        "uf": "SP",
        "latitude": -21.414765,
        "longitude": -50.076855,
        "empresa": "CLARO",
        "cnpj": 66970229000167,
        "data-dados": "2021-07",
        "pf-ou-pj": "Pessoa Física",
        "info-tecnologia": [
            {
                "tecnologia": "FTTH",
                "tipo-de-Produto": "INTERNET",
                "meio-de-acesso": "Fibra",
                "quantidade-acesso": 1793
            }
        ]
    },
    {
        "identifier": "66970229000167-Peruíbe-SP-CLARO-Pessoa Física",
        "cidade": "Peruíbe",
        "uf": "SP",
        "latitude": -24.311974,
        "longitude": -47.0012,
        "empresa": "CLARO",
        "cnpj": 66970229000167,
        "data-dados": "2021-07",
        "pf-ou-pj": "Pessoa Física",
        "info-tecnologia": [
            {
                "tecnologia": "FTTH",
                "tipo-de-Produto": "INTERNET",
                "meio-de-acesso": "Fibra",
                "quantidade-acesso": 10385
            }
        ]
    },
    {
        "identifier": "66970229000167-Pindamonhangaba-SP-CLARO-Pessoa Física",
        "cidade": "Pindamonhangaba",
        "uf": "SP",
        "latitude": -22.92463,
        "longitude": -45.461264,
        "empresa": "CLARO",
        "cnpj": 66970229000167,
        "data-dados": "2021-07",
        "pf-ou-pj": "Pessoa Física",
        "info-tecnologia": [
            {
                "tecnologia": "HFC",
                "tipo-de-Produto": "INTERNET",
                "meio-de-acesso": "Cabo Coaxial",
                "quantidade-acesso": 21292
            }
        ]
    },
    {
        "identifier": "66970229000167-Piracicaba-SP-CLARO-Pessoa Física",
        "cidade": "Piracicaba",
        "uf": "SP",
        "latitude": -22.733801,
        "longitude": -47.647612,
        "empresa": "CLARO",
        "cnpj": 66970229000167,
        "data-dados": "2021-07",
        "pf-ou-pj": "Pessoa Física",
        "info-tecnologia": [
            {
                "tecnologia": "HFC",
                "tipo-de-Produto": "INTERNET",
                "meio-de-acesso": "Cabo Coaxial",
                "quantidade-acesso": 59112
            }
        ]
    },
    {
        "identifier": "66970229000167-Pirassununga-SP-CLARO-Pessoa Física",
        "cidade": "Pirassununga",
        "uf": "SP",
        "latitude": -21.995982,
        "longitude": -47.425746,
        "empresa": "CLARO",
        "cnpj": 66970229000167,
        "data-dados": "2021-07",
        "pf-ou-pj": "Pessoa Física",
        "info-tecnologia": [
            {
                "tecnologia": "FTTH",
                "tipo-de-Produto": "INTERNET",
                "meio-de-acesso": "Fibra",
                "quantidade-acesso": 1
            }
        ]
    },
    {
        "identifier": "66970229000167-Porto Feliz-SP-CLARO-Pessoa Física",
        "cidade": "Porto Feliz",
        "uf": "SP",
        "latitude": -23.209318,
        "longitude": -47.52512,
        "empresa": "CLARO",
        "cnpj": 66970229000167,
        "data-dados": "2021-07",
        "pf-ou-pj": "Pessoa Física",
        "info-tecnologia": [
            {
                "tecnologia": "HFC",
                "tipo-de-Produto": "INTERNET",
                "meio-de-acesso": "Cabo Coaxial",
                "quantidade-acesso": 4977
            }
        ]
    },
    {
        "identifier": "66970229000167-Porto Ferreira-SP-CLARO-Pessoa Física",
        "cidade": "Porto Ferreira",
        "uf": "SP",
        "latitude": -21.849814,
        "longitude": -47.487034,
        "empresa": "CLARO",
        "cnpj": 66970229000167,
        "data-dados": "2021-07",
        "pf-ou-pj": "Pessoa Física",
        "info-tecnologia": [
            {
                "tecnologia": "FTTH",
                "tipo-de-Produto": "INTERNET",
                "meio-de-acesso": "Fibra",
                "quantidade-acesso": 1
            }
        ]
    },
    {
        "identifier": "66970229000167-Potim-SP-CLARO-Pessoa Física",
        "cidade": "Potim",
        "uf": "SP",
        "latitude": -22.834327,
        "longitude": -45.255205,
        "empresa": "CLARO",
        "cnpj": 66970229000167,
        "data-dados": "2021-07",
        "pf-ou-pj": "Pessoa Física",
        "info-tecnologia": [
            {
                "tecnologia": "HFC",
                "tipo-de-Produto": "INTERNET",
                "meio-de-acesso": "Cabo Coaxial",
                "quantidade-acesso": 967
            }
        ]
    },
    {
        "identifier": "66970229000167-Poá-SP-CLARO-Pessoa Física",
        "cidade": "Poá",
        "uf": "SP",
        "latitude": -23.533285,
        "longitude": -46.347292,
        "empresa": "CLARO",
        "cnpj": 66970229000167,
        "data-dados": "2021-07",
        "pf-ou-pj": "Pessoa Física",
        "info-tecnologia": [
            {
                "tecnologia": "HFC",
                "tipo-de-Produto": "INTERNET",
                "meio-de-acesso": "Cabo Coaxial",
                "quantidade-acesso": 3722
            }
        ]
    },
    {
        "identifier": "66970229000167-Praia Grande-SP-CLARO-Pessoa Física",
        "cidade": "Praia Grande",
        "uf": "SP",
        "latitude": -24.008378,
        "longitude": -46.412057,
        "empresa": "CLARO",
        "cnpj": 66970229000167,
        "data-dados": "2021-07",
        "pf-ou-pj": "Pessoa Física",
        "info-tecnologia": [
            {
                "tecnologia": "HFC",
                "tipo-de-Produto": "INTERNET",
                "meio-de-acesso": "Cabo Coaxial",
                "quantidade-acesso": 48413
            }
        ]
    },
    {
        "identifier": "66970229000167-Presidente Bernardes-SP-CLARO-Pessoa Física",
        "cidade": "Presidente Bernardes",
        "uf": "SP",
        "latitude": -22.008198,
        "longitude": -51.556507,
        "empresa": "CLARO",
        "cnpj": 66970229000167,
        "data-dados": "2021-07",
        "pf-ou-pj": "Pessoa Física",
        "info-tecnologia": [
            {
                "tecnologia": "FTTH",
                "tipo-de-Produto": "INTERNET",
                "meio-de-acesso": "Fibra",
                "quantidade-acesso": 568
            }
        ]
    },
    {
        "identifier": "66970229000167-Presidente Prudente-SP-CLARO-Pessoa Física",
        "cidade": "Presidente Prudente",
        "uf": "SP",
        "latitude": -22.120654,
        "longitude": -51.392526,
        "empresa": "CLARO",
        "cnpj": 66970229000167,
        "data-dados": "2021-07",
        "pf-ou-pj": "Pessoa Física",
        "info-tecnologia": [
            {
                "tecnologia": "HFC",
                "tipo-de-Produto": "INTERNET",
                "meio-de-acesso": "Cabo Coaxial",
                "quantidade-acesso": 8218
            }
        ]
    },
    {
        "identifier": "66970229000167-Rafard-SP-CLARO-Pessoa Física",
        "cidade": "Rafard",
        "uf": "SP",
        "latitude": -23.010508,
        "longitude": -47.531795,
        "empresa": "CLARO",
        "cnpj": 66970229000167,
        "data-dados": "2021-07",
        "pf-ou-pj": "Pessoa Física",
        "info-tecnologia": [
            {
                "tecnologia": "HFC",
                "tipo-de-Produto": "INTERNET",
                "meio-de-acesso": "Cabo Coaxial",
                "quantidade-acesso": 908
            }
        ]
    },
    {
        "identifier": "66970229000167-Ribeirão Pires-SP-CLARO-Pessoa Física",
        "cidade": "Ribeirão Pires",
        "uf": "SP",
        "latitude": -23.706669,
        "longitude": -46.405805,
        "empresa": "CLARO",
        "cnpj": 66970229000167,
        "data-dados": "2021-07",
        "pf-ou-pj": "Pessoa Física",
        "info-tecnologia": [
            {
                "tecnologia": "FTTH",
                "tipo-de-Produto": "INTERNET",
                "meio-de-acesso": "Fibra",
                "quantidade-acesso": 5361
            }
        ]
    },
    {
        "identifier": "66970229000167-Ribeirão Preto-SP-CLARO-Pessoa Física",
        "cidade": "Ribeirão Preto",
        "uf": "SP",
        "latitude": -21.169923,
        "longitude": -47.809875,
        "empresa": "CLARO",
        "cnpj": 66970229000167,
        "data-dados": "2021-07",
        "pf-ou-pj": "Pessoa Física",
        "info-tecnologia": [
            {
                "tecnologia": "HFC",
                "tipo-de-Produto": "INTERNET",
                "meio-de-acesso": "Cabo Coaxial",
                "quantidade-acesso": 96204
            }
        ]
    },
    {
        "identifier": "66970229000167-Rio Claro-SP-CLARO-Pessoa Física",
        "cidade": "Rio Claro",
        "uf": "SP",
        "latitude": -22.398378,
        "longitude": -47.554632,
        "empresa": "CLARO",
        "cnpj": 66970229000167,
        "data-dados": "2021-07",
        "pf-ou-pj": "Pessoa Física",
        "info-tecnologia": [
            {
                "tecnologia": "HFC",
                "tipo-de-Produto": "INTERNET",
                "meio-de-acesso": "Cabo Coaxial",
                "quantidade-acesso": 19967
            }
        ]
    },
    {
        "identifier": "66970229000167-Salto-SP-CLARO-Pessoa Física",
        "cidade": "Salto",
        "uf": "SP",
        "latitude": -23.199592,
        "longitude": -47.293087,
        "empresa": "CLARO",
        "cnpj": 66970229000167,
        "data-dados": "2021-07",
        "pf-ou-pj": "Pessoa Física",
        "info-tecnologia": [
            {
                "tecnologia": "HFC",
                "tipo-de-Produto": "INTERNET",
                "meio-de-acesso": "Cabo Coaxial",
                "quantidade-acesso": 13018
            }
        ]
    },
    {
        "identifier": "66970229000167-Santa Bárbara d'Oeste-SP-CLARO-Pessoa Física",
        "cidade": "Santa Bárbara d'Oeste",
        "uf": "SP",
        "latitude": -22.755543,
        "longitude": -47.55047,
        "empresa": "CLARO",
        "cnpj": 66970229000167,
        "data-dados": "2021-07",
        "pf-ou-pj": "Pessoa Física",
        "info-tecnologia": [
            {
                "tecnologia": "HFC",
                "tipo-de-Produto": "INTERNET",
                "meio-de-acesso": "Cabo Coaxial",
                "quantidade-acesso": 25612
            }
        ]
    },
    {
        "identifier": "66970229000167-Santa Cruz do Rio Pardo-SP-CLARO-Pessoa Física",
        "cidade": "Santa Cruz do Rio Pardo",
        "uf": "SP",
        "latitude": -22.89875,
        "longitude": -49.635444,
        "empresa": "CLARO",
        "cnpj": 66970229000167,
        "data-dados": "2021-07",
        "pf-ou-pj": "Pessoa Física",
        "info-tecnologia": [
            {
                "tecnologia": "FTTH",
                "tipo-de-Produto": "INTERNET",
                "meio-de-acesso": "Fibra",
                "quantidade-acesso": 515
            }
        ]
    },
    {
        "identifier": "66970229000167-Santana de Parnaíba-SP-CLARO-Pessoa Física",
        "cidade": "Santana de Parnaíba",
        "uf": "SP",
        "latitude": -23.442514,
        "longitude": -46.922215,
        "empresa": "CLARO",
        "cnpj": 66970229000167,
        "data-dados": "2021-07",
        "pf-ou-pj": "Pessoa Física",
        "info-tecnologia": [
            {
                "tecnologia": "HFC",
                "tipo-de-Produto": "INTERNET",
                "meio-de-acesso": "Cabo Coaxial",
                "quantidade-acesso": 11138
            }
        ]
    },
    {
        "identifier": "66970229000167-Santo André-SP-CLARO-Pessoa Física",
        "cidade": "Santo André",
        "uf": "SP",
        "latitude": -23.67373,
        "longitude": -46.543154,
        "empresa": "CLARO",
        "cnpj": 66970229000167,
        "data-dados": "2021-07",
        "pf-ou-pj": "Pessoa Física",
        "info-tecnologia": [
            {
                "tecnologia": "HFC",
                "tipo-de-Produto": "INTERNET",
                "meio-de-acesso": "Cabo Coaxial",
                "quantidade-acesso": 128387
            }
        ]
    },
    {
        "identifier": "66970229000167-Santos-SP-CLARO-Pessoa Física",
        "cidade": "Santos",
        "uf": "SP",
        "latitude": -23.953543,
        "longitude": -46.335042,
        "empresa": "CLARO",
        "cnpj": 66970229000167,
        "data-dados": "2021-07",
        "pf-ou-pj": "Pessoa Física",
        "info-tecnologia": [
            {
                "tecnologia": "HFC",
                "tipo-de-Produto": "INTERNET",
                "meio-de-acesso": "Cabo Coaxial",
                "quantidade-acesso": 104670
            }
        ]
    },
    {
        "identifier": "66970229000167-Serra Negra-SP-CLARO-Pessoa Física",
        "cidade": "Serra Negra",
        "uf": "SP",
        "latitude": -22.613941,
        "longitude": -46.703271,
        "empresa": "CLARO",
        "cnpj": 66970229000167,
        "data-dados": "2021-07",
        "pf-ou-pj": "Pessoa Física",
        "info-tecnologia": [
            {
                "tecnologia": "FTTH",
                "tipo-de-Produto": "INTERNET",
                "meio-de-acesso": "Fibra",
                "quantidade-acesso": 1944
            }
        ]
    },
    {
        "identifier": "66970229000167-Serrana-SP-CLARO-Pessoa Física",
        "cidade": "Serrana",
        "uf": "SP",
        "latitude": -21.204336,
        "longitude": -47.595239,
        "empresa": "CLARO",
        "cnpj": 66970229000167,
        "data-dados": "2021-07",
        "pf-ou-pj": "Pessoa Física",
        "info-tecnologia": [
            {
                "tecnologia": "FTTH",
                "tipo-de-Produto": "INTERNET",
                "meio-de-acesso": "Fibra",
                "quantidade-acesso": 1104
            }
        ]
    },
    {
        "identifier": "66970229000167-Sertãozinho-SP-CLARO-Pessoa Física",
        "cidade": "Sertãozinho",
        "uf": "SP",
        "latitude": -21.131596,
        "longitude": -47.987496,
        "empresa": "CLARO",
        "cnpj": 66970229000167,
        "data-dados": "2021-07",
        "pf-ou-pj": "Pessoa Física",
        "info-tecnologia": [
            {
                "tecnologia": "HFC",
                "tipo-de-Produto": "INTERNET",
                "meio-de-acesso": "Cabo Coaxial",
                "quantidade-acesso": 11783
            }
        ]
    },
    {
        "identifier": "66970229000167-Sorocaba-SP-CLARO-Pessoa Física",
        "cidade": "Sorocaba",
        "uf": "SP",
        "latitude": -23.496886,
        "longitude": -47.445073,
        "empresa": "CLARO",
        "cnpj": 66970229000167,
        "data-dados": "2021-07",
        "pf-ou-pj": "Pessoa Física",
        "info-tecnologia": [
            {
                "tecnologia": "HFC",
                "tipo-de-Produto": "INTERNET",
                "meio-de-acesso": "Cabo Coaxial",
                "quantidade-acesso": 134789
            }
        ]
    },
    {
        "identifier": "66970229000167-Sumaré-SP-CLARO-Pessoa Física",
        "cidade": "Sumaré",
        "uf": "SP",
        "latitude": -22.820416,
        "longitude": -47.272823,
        "empresa": "CLARO",
        "cnpj": 66970229000167,
        "data-dados": "2021-07",
        "pf-ou-pj": "Pessoa Física",
        "info-tecnologia": [
            {
                "tecnologia": "HFC",
                "tipo-de-Produto": "INTERNET",
                "meio-de-acesso": "Cabo Coaxial",
                "quantidade-acesso": 7573
            }
        ]
    },
    {
        "identifier": "66970229000167-Suzano-SP-CLARO-Pessoa Física",
        "cidade": "Suzano",
        "uf": "SP",
        "latitude": -23.544828,
        "longitude": -46.311181,
        "empresa": "CLARO",
        "cnpj": 66970229000167,
        "data-dados": "2021-07",
        "pf-ou-pj": "Pessoa Física",
        "info-tecnologia": [
            {
                "tecnologia": "HFC",
                "tipo-de-Produto": "INTERNET",
                "meio-de-acesso": "Cabo Coaxial",
                "quantidade-acesso": 8020
            }
        ]
    },
    {
        "identifier": "66970229000167-São Bernardo do Campo-SP-CLARO-Pessoa Física",
        "cidade": "São Bernardo do Campo",
        "uf": "SP",
        "latitude": -23.691412,
        "longitude": -46.564617,
        "empresa": "CLARO",
        "cnpj": 66970229000167,
        "data-dados": "2021-07",
        "pf-ou-pj": "Pessoa Física",
        "info-tecnologia": [
            {
                "tecnologia": "HFC",
                "tipo-de-Produto": "INTERNET",
                "meio-de-acesso": "Cabo Coaxial",
                "quantidade-acesso": 116269
            }
        ]
    },
    {
        "identifier": "66970229000167-São Caetano do Sul-SP-CLARO-Pessoa Física",
        "cidade": "São Caetano do Sul",
        "uf": "SP",
        "latitude": -23.62287,
        "longitude": -46.554797,
        "empresa": "CLARO",
        "cnpj": 66970229000167,
        "data-dados": "2021-07",
        "pf-ou-pj": "Pessoa Física",
        "info-tecnologia": [
            {
                "tecnologia": "HFC",
                "tipo-de-Produto": "INTERNET",
                "meio-de-acesso": "Cabo Coaxial",
                "quantidade-acesso": 35693
            }
        ]
    },
    {
        "identifier": "66970229000167-São Carlos-SP-CLARO-Pessoa Física",
        "cidade": "São Carlos",
        "uf": "SP",
        "latitude": -22.017395,
        "longitude": -47.885971,
        "empresa": "CLARO",
        "cnpj": 66970229000167,
        "data-dados": "2021-07",
        "pf-ou-pj": "Pessoa Física",
        "info-tecnologia": [
            {
                "tecnologia": "HFC",
                "tipo-de-Produto": "INTERNET",
                "meio-de-acesso": "Cabo Coaxial",
                "quantidade-acesso": 51042
            }
        ]
    },
    {
        "identifier": "66970229000167-São Joaquim da Barra-SP-CLARO-Pessoa Física",
        "cidade": "São Joaquim da Barra",
        "uf": "SP",
        "latitude": -20.581158,
        "longitude": -47.859316,
        "empresa": "CLARO",
        "cnpj": 66970229000167,
        "data-dados": "2021-07",
        "pf-ou-pj": "Pessoa Física",
        "info-tecnologia": [
            {
                "tecnologia": "FTTH",
                "tipo-de-Produto": "INTERNET",
                "meio-de-acesso": "Fibra",
                "quantidade-acesso": 3681
            }
        ]
    },
    {
        "identifier": "66970229000167-São José do Rio Pardo-SP-CLARO-Pessoa Física",
        "cidade": "São José do Rio Pardo",
        "uf": "SP",
        "latitude": -21.595288,
        "longitude": -46.887303,
        "empresa": "CLARO",
        "cnpj": 66970229000167,
        "data-dados": "2021-07",
        "pf-ou-pj": "Pessoa Física",
        "info-tecnologia": [
            {
                "tecnologia": "FTTH",
                "tipo-de-Produto": "INTERNET",
                "meio-de-acesso": "Fibra",
                "quantidade-acesso": 1210
            }
        ]
    },
    {
        "identifier": "66970229000167-São José do Rio Preto-SP-CLARO-Pessoa Física",
        "cidade": "São José do Rio Preto",
        "uf": "SP",
        "latitude": -20.811289,
        "longitude": -49.375767,
        "empresa": "CLARO",
        "cnpj": 66970229000167,
        "data-dados": "2021-07",
        "pf-ou-pj": "Pessoa Física",
        "info-tecnologia": [
            {
                "tecnologia": "HFC",
                "tipo-de-Produto": "INTERNET",
                "meio-de-acesso": "Cabo Coaxial",
                "quantidade-acesso": 63021
            }
        ]
    },
    {
        "identifier": "66970229000167-São José dos Campos-SP-CLARO-Pessoa Física",
        "cidade": "São José dos Campos",
        "uf": "SP",
        "latitude": -23.189554,
        "longitude": -45.884115,
        "empresa": "CLARO",
        "cnpj": 66970229000167,
        "data-dados": "2021-07",
        "pf-ou-pj": "Pessoa Física",
        "info-tecnologia": [
            {
                "tecnologia": "HFC",
                "tipo-de-Produto": "INTERNET",
                "meio-de-acesso": "Cabo Coaxial",
                "quantidade-acesso": 96948
            }
        ]
    },
    {
        "identifier": "66970229000167-São Paulo-SP-CLARO-Pessoa Física",
        "cidade": "São Paulo",
        "uf": "SP",
        "latitude": -23.532905,
        "longitude": -46.63952,
        "empresa": "CLARO",
        "cnpj": 66970229000167,
        "data-dados": "2021-07",
        "pf-ou-pj": "Pessoa Física",
        "info-tecnologia": [
            {
                "tecnologia": "HFC",
                "tipo-de-Produto": "INTERNET",
                "meio-de-acesso": "Cabo Coaxial",
                "quantidade-acesso": 1429756
            }
        ]
    },
    {
        "identifier": "66970229000167-São Roque-SP-CLARO-Pessoa Física",
        "cidade": "São Roque",
        "uf": "SP",
        "latitude": -23.522598,
        "longitude": -47.13567,
        "empresa": "CLARO",
        "cnpj": 66970229000167,
        "data-dados": "2021-07",
        "pf-ou-pj": "Pessoa Física",
        "info-tecnologia": [
            {
                "tecnologia": "FTTH",
                "tipo-de-Produto": "INTERNET",
                "meio-de-acesso": "Fibra",
                "quantidade-acesso": 6813
            }
        ]
    },
    {
        "identifier": "66970229000167-São Sebastião-SP-CLARO-Pessoa Física",
        "cidade": "São Sebastião",
        "uf": "SP",
        "latitude": -23.795059,
        "longitude": -45.414314,
        "empresa": "CLARO",
        "cnpj": 66970229000167,
        "data-dados": "2021-07",
        "pf-ou-pj": "Pessoa Física",
        "info-tecnologia": [
            {
                "tecnologia": "FTTH",
                "tipo-de-Produto": "INTERNET",
                "meio-de-acesso": "Fibra",
                "quantidade-acesso": 6208
            }
        ]
    },
    {
        "identifier": "66970229000167-São Vicente-SP-CLARO-Pessoa Física",
        "cidade": "São Vicente",
        "uf": "SP",
        "latitude": -23.957353,
        "longitude": -46.388333,
        "empresa": "CLARO",
        "cnpj": 66970229000167,
        "data-dados": "2021-07",
        "pf-ou-pj": "Pessoa Física",
        "info-tecnologia": [
            {
                "tecnologia": "HFC",
                "tipo-de-Produto": "INTERNET",
                "meio-de-acesso": "Cabo Coaxial",
                "quantidade-acesso": 30728
            }
        ]
    },
    {
        "identifier": "66970229000167-Taboão da Serra-SP-CLARO-Pessoa Física",
        "cidade": "Taboão da Serra",
        "uf": "SP",
        "latitude": -23.601867,
        "longitude": -46.752637,
        "empresa": "CLARO",
        "cnpj": 66970229000167,
        "data-dados": "2021-07",
        "pf-ou-pj": "Pessoa Física",
        "info-tecnologia": [
            {
                "tecnologia": "HFC",
                "tipo-de-Produto": "INTERNET",
                "meio-de-acesso": "Cabo Coaxial",
                "quantidade-acesso": 14665
            }
        ]
    },
    {
        "identifier": "66970229000167-Tatuí-SP-CLARO-Pessoa Física",
        "cidade": "Tatuí",
        "uf": "SP",
        "latitude": -23.348731,
        "longitude": -47.84612,
        "empresa": "CLARO",
        "cnpj": 66970229000167,
        "data-dados": "2021-07",
        "pf-ou-pj": "Pessoa Física",
        "info-tecnologia": [
            {
                "tecnologia": "FTTH",
                "tipo-de-Produto": "INTERNET",
                "meio-de-acesso": "Fibra",
                "quantidade-acesso": 9150
            }
        ]
    },
    {
        "identifier": "66970229000167-Taubaté-SP-CLARO-Pessoa Física",
        "cidade": "Taubaté",
        "uf": "SP",
        "latitude": -23.010414,
        "longitude": -45.55926,
        "empresa": "CLARO",
        "cnpj": 66970229000167,
        "data-dados": "2021-07",
        "pf-ou-pj": "Pessoa Física",
        "info-tecnologia": [
            {
                "tecnologia": "HFC",
                "tipo-de-Produto": "INTERNET",
                "meio-de-acesso": "Cabo Coaxial",
                "quantidade-acesso": 44187
            }
        ]
    },
    {
        "identifier": "66970229000167-Tietê-SP-CLARO-Pessoa Física",
        "cidade": "Tietê",
        "uf": "SP",
        "latitude": -23.110098,
        "longitude": -47.716378,
        "empresa": "CLARO",
        "cnpj": 66970229000167,
        "data-dados": "2021-07",
        "pf-ou-pj": "Pessoa Física",
        "info-tecnologia": [
            {
                "tecnologia": "HFC",
                "tipo-de-Produto": "INTERNET",
                "meio-de-acesso": "Cabo Coaxial",
                "quantidade-acesso": 1914
            }
        ]
    },
    {
        "identifier": "66970229000167-Tremembé-SP-CLARO-Pessoa Física",
        "cidade": "Tremembé",
        "uf": "SP",
        "latitude": -22.95714,
        "longitude": -45.547526,
        "empresa": "CLARO",
        "cnpj": 66970229000167,
        "data-dados": "2021-07",
        "pf-ou-pj": "Pessoa Física",
        "info-tecnologia": [
            {
                "tecnologia": "FTTH",
                "tipo-de-Produto": "INTERNET",
                "meio-de-acesso": "Fibra",
                "quantidade-acesso": 5796
            }
        ]
    },
    {
        "identifier": "66970229000167-Ubatuba-SP-CLARO-Pessoa Física",
        "cidade": "Ubatuba",
        "uf": "SP",
        "latitude": -23.433162,
        "longitude": -45.083415,
        "empresa": "CLARO",
        "cnpj": 66970229000167,
        "data-dados": "2021-07",
        "pf-ou-pj": "Pessoa Física",
        "info-tecnologia": [
            {
                "tecnologia": "FTTH",
                "tipo-de-Produto": "INTERNET",
                "meio-de-acesso": "Fibra",
                "quantidade-acesso": 7406
            }
        ]
    },
    {
        "identifier": "66970229000167-Valinhos-SP-CLARO-Pessoa Física",
        "cidade": "Valinhos",
        "uf": "SP",
        "latitude": -22.969805,
        "longitude": -46.997367,
        "empresa": "CLARO",
        "cnpj": 66970229000167,
        "data-dados": "2021-07",
        "pf-ou-pj": "Pessoa Física",
        "info-tecnologia": [
            {
                "tecnologia": "HFC",
                "tipo-de-Produto": "INTERNET",
                "meio-de-acesso": "Cabo Coaxial",
                "quantidade-acesso": 16468
            }
        ]
    },
    {
        "identifier": "66970229000167-Vargem Grande Paulista-SP-CLARO-Pessoa Física",
        "cidade": "Vargem Grande Paulista",
        "uf": "SP",
        "latitude": -23.599338,
        "longitude": -47.022038,
        "empresa": "CLARO",
        "cnpj": 66970229000167,
        "data-dados": "2021-07",
        "pf-ou-pj": "Pessoa Física",
        "info-tecnologia": [
            {
                "tecnologia": "HFC",
                "tipo-de-Produto": "INTERNET",
                "meio-de-acesso": "Cabo Coaxial",
                "quantidade-acesso": 4077
            }
        ]
    },
    {
        "identifier": "66970229000167-Vinhedo-SP-CLARO-Pessoa Física",
        "cidade": "Vinhedo",
        "uf": "SP",
        "latitude": -23.030184,
        "longitude": -46.983312,
        "empresa": "CLARO",
        "cnpj": 66970229000167,
        "data-dados": "2021-07",
        "pf-ou-pj": "Pessoa Física",
        "info-tecnologia": [
            {
                "tecnologia": "HFC",
                "tipo-de-Produto": "INTERNET",
                "meio-de-acesso": "Cabo Coaxial",
                "quantidade-acesso": 2721
            }
        ]
    },
    {
        "identifier": "66970229000167-Votorantim-SP-CLARO-Pessoa Física",
        "cidade": "Votorantim",
        "uf": "SP",
        "latitude": -23.54459,
        "longitude": -47.438753,
        "empresa": "CLARO",
        "cnpj": 66970229000167,
        "data-dados": "2021-07",
        "pf-ou-pj": "Pessoa Física",
        "info-tecnologia": [
            {
                "tecnologia": "HFC",
                "tipo-de-Produto": "INTERNET",
                "meio-de-acesso": "Cabo Coaxial",
                "quantidade-acesso": 11724
            }
        ]
    },
    {
        "identifier": "66970229000167-Várzea Paulista-SP-CLARO-Pessoa Física",
        "cidade": "Várzea Paulista",
        "uf": "SP",
        "latitude": -23.213582,
        "longitude": -46.823444,
        "empresa": "CLARO",
        "cnpj": 66970229000167,
        "data-dados": "2021-07",
        "pf-ou-pj": "Pessoa Física",
        "info-tecnologia": [
            {
                "tecnologia": "FTTH",
                "tipo-de-Produto": "INTERNET",
                "meio-de-acesso": "Fibra",
                "quantidade-acesso": 1094
            }
        ]
    }
]