[
    {
        "identifier": "76535764000143-Afonso Cláudio-ES-Oi S.a. - em Recuperacao Judicial-Pessoa Física",
        "cidade": "Afonso Cláudio",
        "uf": "ES",
        "latitude": -20.077841,
        "longitude": -41.12606,
        "empresa": "Oi S.a. - em Recuperacao Judicial",
        "cnpj": 76535764000143,
        "data-dados": "2025-01",
        "pf-ou-pj": "Pessoa Física",
        "info-tecnologia": [
            {
                "tecnologia": "ADSL1",
                "tipo-de-Produto": "INTERNET",
                "meio-de-acesso": "Cabo Metálico",
                "quantidade-acesso": 3
            }
        ]
    },
    {
        "identifier": "76535764000143-Alto Rio Novo-ES-Oi S.a. - em Recuperacao Judicial-Pessoa Física",
        "cidade": "Alto Rio Novo",
        "uf": "ES",
        "latitude": -19.061797,
        "longitude": -41.020909,
        "empresa": "Oi S.a. - em Recuperacao Judicial",
        "cnpj": 76535764000143,
        "data-dados": "2025-01",
        "pf-ou-pj": "Pessoa Física",
        "info-tecnologia": [
            {
                "tecnologia": "ADSL1",
                "tipo-de-Produto": "INTERNET",
                "meio-de-acesso": "Cabo Metálico",
                "quantidade-acesso": 1
            },
            {
                "tecnologia": "ADSL2",
                "tipo-de-Produto": "INTERNET",
                "meio-de-acesso": "Cabo Metálico",
                "quantidade-acesso": 2
            }
        ]
    },
    {
        "identifier": "76535764000143-Anchieta-ES-Oi S.a. - em Recuperacao Judicial-Pessoa Física",
        "cidade": "Anchieta",
        "uf": "ES",
        "latitude": -20.795499,
        "longitude": -40.642545,
        "empresa": "Oi S.a. - em Recuperacao Judicial",
        "cnpj": 76535764000143,
        "data-dados": "2025-01",
        "pf-ou-pj": "Pessoa Física",
        "info-tecnologia": [
            {
                "tecnologia": "ADSL1",
                "tipo-de-Produto": "INTERNET",
                "meio-de-acesso": "Cabo Metálico",
                "quantidade-acesso": 1
            },
            {
                "tecnologia": "ADSL2",
                "tipo-de-Produto": "INTERNET",
                "meio-de-acesso": "Cabo Metálico",
                "quantidade-acesso": 8
            }
        ]
    },
    {
        "identifier": "76535764000143-Aracruz-ES-Oi S.a. - em Recuperacao Judicial-Pessoa Física",
        "cidade": "Aracruz",
        "uf": "ES",
        "latitude": -19.820045,
        "longitude": -40.276441,
        "empresa": "Oi S.a. - em Recuperacao Judicial",
        "cnpj": 76535764000143,
        "data-dados": "2025-01",
        "pf-ou-pj": "Pessoa Física",
        "info-tecnologia": [
            {
                "tecnologia": "ADSL1",
                "tipo-de-Produto": "INTERNET",
                "meio-de-acesso": "Cabo Metálico",
                "quantidade-acesso": 1
            },
            {
                "tecnologia": "ADSL2",
                "tipo-de-Produto": "INTERNET",
                "meio-de-acesso": "Cabo Metálico",
                "quantidade-acesso": 2
            }
        ]
    },
    {
        "identifier": "76535764000143-Atilio Vivacqua-ES-Oi S.a. - em Recuperacao Judicial-Pessoa Física",
        "cidade": "Atilio Vivacqua",
        "uf": "ES",
        "latitude": -20.912974,
        "longitude": -41.198576,
        "empresa": "Oi S.a. - em Recuperacao Judicial",
        "cnpj": 76535764000143,
        "data-dados": "2025-01",
        "pf-ou-pj": "Pessoa Física",
        "info-tecnologia": [
            {
                "tecnologia": "ADSL1",
                "tipo-de-Produto": "INTERNET",
                "meio-de-acesso": "Cabo Metálico",
                "quantidade-acesso": 1
            },
            {
                "tecnologia": "ADSL2",
                "tipo-de-Produto": "INTERNET",
                "meio-de-acesso": "Cabo Metálico",
                "quantidade-acesso": 1
            }
        ]
    },
    {
        "identifier": "76535764000143-Baixo Guandu-ES-Oi S.a. - em Recuperacao Judicial-Pessoa Física",
        "cidade": "Baixo Guandu",
        "uf": "ES",
        "latitude": -19.521283,
        "longitude": -41.010913,
        "empresa": "Oi S.a. - em Recuperacao Judicial",
        "cnpj": 76535764000143,
        "data-dados": "2025-01",
        "pf-ou-pj": "Pessoa Física",
        "info-tecnologia": [
            {
                "tecnologia": "ADSL1",
                "tipo-de-Produto": "INTERNET",
                "meio-de-acesso": "Cabo Metálico",
                "quantidade-acesso": 1
            },
            {
                "tecnologia": "ADSL2",
                "tipo-de-Produto": "INTERNET",
                "meio-de-acesso": "Cabo Metálico",
                "quantidade-acesso": 13
            }
        ]
    },
    {
        "identifier": "76535764000143-Barra de São Francisco-ES-Oi S.a. - em Recuperacao Judicial-Pessoa Física",
        "cidade": "Barra de São Francisco",
        "uf": "ES",
        "latitude": -18.75484,
        "longitude": -40.896456,
        "empresa": "Oi S.a. - em Recuperacao Judicial",
        "cnpj": 76535764000143,
        "data-dados": "2025-01",
        "pf-ou-pj": "Pessoa Física",
        "info-tecnologia": [
            {
                "tecnologia": "ADSL1",
                "tipo-de-Produto": "INTERNET",
                "meio-de-acesso": "Cabo Metálico",
                "quantidade-acesso": 3
            },
            {
                "tecnologia": "ADSL2",
                "tipo-de-Produto": "INTERNET",
                "meio-de-acesso": "Cabo Metálico",
                "quantidade-acesso": 26
            }
        ]
    },
    {
        "identifier": "76535764000143-Boa Esperança-ES-Oi S.a. - em Recuperacao Judicial-Pessoa Física",
        "cidade": "Boa Esperança",
        "uf": "ES",
        "latitude": -18.539495,
        "longitude": -40.302521,
        "empresa": "Oi S.a. - em Recuperacao Judicial",
        "cnpj": 76535764000143,
        "data-dados": "2025-01",
        "pf-ou-pj": "Pessoa Física",
        "info-tecnologia": [
            {
                "tecnologia": "ADSL2",
                "tipo-de-Produto": "INTERNET",
                "meio-de-acesso": "Cabo Metálico",
                "quantidade-acesso": 1
            }
        ]
    },
    {
        "identifier": "76535764000143-Brejetuba-ES-Oi S.a. - em Recuperacao Judicial-Pessoa Física",
        "cidade": "Brejetuba",
        "uf": "ES",
        "latitude": -20.139489,
        "longitude": -41.29541,
        "empresa": "Oi S.a. - em Recuperacao Judicial",
        "cnpj": 76535764000143,
        "data-dados": "2025-01",
        "pf-ou-pj": "Pessoa Física",
        "info-tecnologia": [
            {
                "tecnologia": "ADSL1",
                "tipo-de-Produto": "INTERNET",
                "meio-de-acesso": "Cabo Metálico",
                "quantidade-acesso": 1
            }
        ]
    },
    {
        "identifier": "76535764000143-Cachoeiro de Itapemirim-ES-Oi S.a. - em Recuperacao Judicial-Pessoa Física",
        "cidade": "Cachoeiro de Itapemirim",
        "uf": "ES",
        "latitude": -20.846212,
        "longitude": -41.119829,
        "empresa": "Oi S.a. - em Recuperacao Judicial",
        "cnpj": 76535764000143,
        "data-dados": "2025-01",
        "pf-ou-pj": "Pessoa Física",
        "info-tecnologia": [
            {
                "tecnologia": "FTTH",
                "tipo-de-Produto": "INTERNET",
                "meio-de-acesso": "Fibra",
                "quantidade-acesso": 6219
            }
        ]
    },
    {
        "identifier": "76535764000143-Cariacica-ES-Oi S.a. - em Recuperacao Judicial-Pessoa Física",
        "cidade": "Cariacica",
        "uf": "ES",
        "latitude": -20.263202,
        "longitude": -40.416549,
        "empresa": "Oi S.a. - em Recuperacao Judicial",
        "cnpj": 76535764000143,
        "data-dados": "2025-01",
        "pf-ou-pj": "Pessoa Física",
        "info-tecnologia": [
            {
                "tecnologia": "ADSL1",
                "tipo-de-Produto": "INTERNET",
                "meio-de-acesso": "Cabo Metálico",
                "quantidade-acesso": 2
            },
            {
                "tecnologia": "ADSL2",
                "tipo-de-Produto": "INTERNET",
                "meio-de-acesso": "Cabo Metálico",
                "quantidade-acesso": 7
            },
            {
                "tecnologia": "FTTH",
                "tipo-de-Produto": "INTERNET",
                "meio-de-acesso": "Fibra",
                "quantidade-acesso": 28728
            }
        ]
    },
    {
        "identifier": "76535764000143-Castelo-ES-Oi S.a. - em Recuperacao Judicial-Pessoa Física",
        "cidade": "Castelo",
        "uf": "ES",
        "latitude": -20.603255,
        "longitude": -41.203133,
        "empresa": "Oi S.a. - em Recuperacao Judicial",
        "cnpj": 76535764000143,
        "data-dados": "2025-01",
        "pf-ou-pj": "Pessoa Física",
        "info-tecnologia": [
            {
                "tecnologia": "ADSL1",
                "tipo-de-Produto": "INTERNET",
                "meio-de-acesso": "Cabo Metálico",
                "quantidade-acesso": 4
            },
            {
                "tecnologia": "ADSL2",
                "tipo-de-Produto": "INTERNET",
                "meio-de-acesso": "Cabo Metálico",
                "quantidade-acesso": 8
            }
        ]
    },
    {
        "identifier": "76535764000143-Colatina-ES-Oi S.a. - em Recuperacao Judicial-Pessoa Física",
        "cidade": "Colatina",
        "uf": "ES",
        "latitude": -19.549316,
        "longitude": -40.626898,
        "empresa": "Oi S.a. - em Recuperacao Judicial",
        "cnpj": 76535764000143,
        "data-dados": "2025-01",
        "pf-ou-pj": "Pessoa Física",
        "info-tecnologia": [
            {
                "tecnologia": "ADSL2",
                "tipo-de-Produto": "INTERNET",
                "meio-de-acesso": "Cabo Metálico",
                "quantidade-acesso": 7
            }
        ]
    },
    {
        "identifier": "76535764000143-Conceição da Barra-ES-Oi S.a. - em Recuperacao Judicial-Pessoa Física",
        "cidade": "Conceição da Barra",
        "uf": "ES",
        "latitude": -18.588306,
        "longitude": -39.736199,
        "empresa": "Oi S.a. - em Recuperacao Judicial",
        "cnpj": 76535764000143,
        "data-dados": "2025-01",
        "pf-ou-pj": "Pessoa Física",
        "info-tecnologia": [
            {
                "tecnologia": "ADSL1",
                "tipo-de-Produto": "INTERNET",
                "meio-de-acesso": "Cabo Metálico",
                "quantidade-acesso": 3
            },
            {
                "tecnologia": "ADSL2",
                "tipo-de-Produto": "INTERNET",
                "meio-de-acesso": "Cabo Metálico",
                "quantidade-acesso": 2
            }
        ]
    },
    {
        "identifier": "76535764000143-Divino de São Lourenço-ES-Oi S.a. - em Recuperacao Judicial-Pessoa Física",
        "cidade": "Divino de São Lourenço",
        "uf": "ES",
        "latitude": -20.622932,
        "longitude": -41.693725,
        "empresa": "Oi S.a. - em Recuperacao Judicial",
        "cnpj": 76535764000143,
        "data-dados": "2025-01",
        "pf-ou-pj": "Pessoa Física",
        "info-tecnologia": [
            {
                "tecnologia": "ADSL2",
                "tipo-de-Produto": "INTERNET",
                "meio-de-acesso": "Cabo Metálico",
                "quantidade-acesso": 2
            }
        ]
    },
    {
        "identifier": "76535764000143-Domingos Martins-ES-Oi S.a. - em Recuperacao Judicial-Pessoa Física",
        "cidade": "Domingos Martins",
        "uf": "ES",
        "latitude": -20.360306,
        "longitude": -40.659425,
        "empresa": "Oi S.a. - em Recuperacao Judicial",
        "cnpj": 76535764000143,
        "data-dados": "2025-01",
        "pf-ou-pj": "Pessoa Física",
        "info-tecnologia": [
            {
                "tecnologia": "ADSL1",
                "tipo-de-Produto": "INTERNET",
                "meio-de-acesso": "Cabo Metálico",
                "quantidade-acesso": 1
            },
            {
                "tecnologia": "ADSL2",
                "tipo-de-Produto": "INTERNET",
                "meio-de-acesso": "Cabo Metálico",
                "quantidade-acesso": 4
            }
        ]
    },
    {
        "identifier": "76535764000143-Dores do Rio Preto-ES-Oi S.a. - em Recuperacao Judicial-Pessoa Física",
        "cidade": "Dores do Rio Preto",
        "uf": "ES",
        "latitude": -20.693119,
        "longitude": -41.840538,
        "empresa": "Oi S.a. - em Recuperacao Judicial",
        "cnpj": 76535764000143,
        "data-dados": "2025-01",
        "pf-ou-pj": "Pessoa Física",
        "info-tecnologia": [
            {
                "tecnologia": "ADSL2",
                "tipo-de-Produto": "INTERNET",
                "meio-de-acesso": "Cabo Metálico",
                "quantidade-acesso": 1
            }
        ]
    },
    {
        "identifier": "76535764000143-Ecoporanga-ES-Oi S.a. - em Recuperacao Judicial-Pessoa Física",
        "cidade": "Ecoporanga",
        "uf": "ES",
        "latitude": -18.370231,
        "longitude": -40.835976,
        "empresa": "Oi S.a. - em Recuperacao Judicial",
        "cnpj": 76535764000143,
        "data-dados": "2025-01",
        "pf-ou-pj": "Pessoa Física",
        "info-tecnologia": [
            {
                "tecnologia": "ADSL1",
                "tipo-de-Produto": "INTERNET",
                "meio-de-acesso": "Cabo Metálico",
                "quantidade-acesso": 3
            },
            {
                "tecnologia": "ADSL2",
                "tipo-de-Produto": "INTERNET",
                "meio-de-acesso": "Cabo Metálico",
                "quantidade-acesso": 2
            }
        ]
    },
    {
        "identifier": "76535764000143-Fundão-ES-Oi S.a. - em Recuperacao Judicial-Pessoa Física",
        "cidade": "Fundão",
        "uf": "ES",
        "latitude": -19.937035,
        "longitude": -40.407759,
        "empresa": "Oi S.a. - em Recuperacao Judicial",
        "cnpj": 76535764000143,
        "data-dados": "2025-01",
        "pf-ou-pj": "Pessoa Física",
        "info-tecnologia": [
            {
                "tecnologia": "ADSL1",
                "tipo-de-Produto": "INTERNET",
                "meio-de-acesso": "Cabo Metálico",
                "quantidade-acesso": 1
            },
            {
                "tecnologia": "ADSL2",
                "tipo-de-Produto": "INTERNET",
                "meio-de-acesso": "Cabo Metálico",
                "quantidade-acesso": 2
            }
        ]
    },
    {
        "identifier": "76535764000143-Guarapari-ES-Oi S.a. - em Recuperacao Judicial-Pessoa Física",
        "cidade": "Guarapari",
        "uf": "ES",
        "latitude": -20.677248,
        "longitude": -40.509253,
        "empresa": "Oi S.a. - em Recuperacao Judicial",
        "cnpj": 76535764000143,
        "data-dados": "2025-01",
        "pf-ou-pj": "Pessoa Física",
        "info-tecnologia": [
            {
                "tecnologia": "ADSL1",
                "tipo-de-Produto": "INTERNET",
                "meio-de-acesso": "Cabo Metálico",
                "quantidade-acesso": 2
            },
            {
                "tecnologia": "ADSL2",
                "tipo-de-Produto": "INTERNET",
                "meio-de-acesso": "Cabo Metálico",
                "quantidade-acesso": 12
            },
            {
                "tecnologia": "FTTH",
                "tipo-de-Produto": "INTERNET",
                "meio-de-acesso": "Fibra",
                "quantidade-acesso": 1
            }
        ]
    },
    {
        "identifier": "76535764000143-Guaçuí-ES-Oi S.a. - em Recuperacao Judicial-Pessoa Física",
        "cidade": "Guaçuí",
        "uf": "ES",
        "latitude": -20.766792,
        "longitude": -41.6734,
        "empresa": "Oi S.a. - em Recuperacao Judicial",
        "cnpj": 76535764000143,
        "data-dados": "2025-01",
        "pf-ou-pj": "Pessoa Física",
        "info-tecnologia": [
            {
                "tecnologia": "ADSL1",
                "tipo-de-Produto": "INTERNET",
                "meio-de-acesso": "Cabo Metálico",
                "quantidade-acesso": 1
            },
            {
                "tecnologia": "ADSL2",
                "tipo-de-Produto": "INTERNET",
                "meio-de-acesso": "Cabo Metálico",
                "quantidade-acesso": 17
            }
        ]
    },
    {
        "identifier": "76535764000143-Ibitirama-ES-Oi S.a. - em Recuperacao Judicial-Pessoa Física",
        "cidade": "Ibitirama",
        "uf": "ES",
        "latitude": -20.546619,
        "longitude": -41.666718,
        "empresa": "Oi S.a. - em Recuperacao Judicial",
        "cnpj": 76535764000143,
        "data-dados": "2025-01",
        "pf-ou-pj": "Pessoa Física",
        "info-tecnologia": [
            {
                "tecnologia": "ADSL1",
                "tipo-de-Produto": "INTERNET",
                "meio-de-acesso": "Cabo Metálico",
                "quantidade-acesso": 1
            }
        ]
    },
    {
        "identifier": "76535764000143-Iconha-ES-Oi S.a. - em Recuperacao Judicial-Pessoa Física",
        "cidade": "Iconha",
        "uf": "ES",
        "latitude": -20.791287,
        "longitude": -40.8132,
        "empresa": "Oi S.a. - em Recuperacao Judicial",
        "cnpj": 76535764000143,
        "data-dados": "2025-01",
        "pf-ou-pj": "Pessoa Física",
        "info-tecnologia": [
            {
                "tecnologia": "ADSL2",
                "tipo-de-Produto": "INTERNET",
                "meio-de-acesso": "Cabo Metálico",
                "quantidade-acesso": 2
            }
        ]
    },
    {
        "identifier": "76535764000143-Irupi-ES-Oi S.a. - em Recuperacao Judicial-Pessoa Física",
        "cidade": "Irupi",
        "uf": "ES",
        "latitude": -20.350122,
        "longitude": -41.644359,
        "empresa": "Oi S.a. - em Recuperacao Judicial",
        "cnpj": 76535764000143,
        "data-dados": "2025-01",
        "pf-ou-pj": "Pessoa Física",
        "info-tecnologia": [
            {
                "tecnologia": "ADSL1",
                "tipo-de-Produto": "INTERNET",
                "meio-de-acesso": "Cabo Metálico",
                "quantidade-acesso": 1
            }
        ]
    },
    {
        "identifier": "76535764000143-Itapemirim-ES-Oi S.a. - em Recuperacao Judicial-Pessoa Física",
        "cidade": "Itapemirim",
        "uf": "ES",
        "latitude": -21.009512,
        "longitude": -40.830669,
        "empresa": "Oi S.a. - em Recuperacao Judicial",
        "cnpj": 76535764000143,
        "data-dados": "2025-01",
        "pf-ou-pj": "Pessoa Física",
        "info-tecnologia": [
            {
                "tecnologia": "ADSL1",
                "tipo-de-Produto": "INTERNET",
                "meio-de-acesso": "Cabo Metálico",
                "quantidade-acesso": 1
            },
            {
                "tecnologia": "ADSL2",
                "tipo-de-Produto": "INTERNET",
                "meio-de-acesso": "Cabo Metálico",
                "quantidade-acesso": 2
            }
        ]
    },
    {
        "identifier": "76535764000143-Iúna-ES-Oi S.a. - em Recuperacao Judicial-Pessoa Física",
        "cidade": "Iúna",
        "uf": "ES",
        "latitude": -20.353135,
        "longitude": -41.53344,
        "empresa": "Oi S.a. - em Recuperacao Judicial",
        "cnpj": 76535764000143,
        "data-dados": "2025-01",
        "pf-ou-pj": "Pessoa Física",
        "info-tecnologia": [
            {
                "tecnologia": "ADSL2",
                "tipo-de-Produto": "INTERNET",
                "meio-de-acesso": "Cabo Metálico",
                "quantidade-acesso": 6
            }
        ]
    },
    {
        "identifier": "76535764000143-Jaguaré-ES-Oi S.a. - em Recuperacao Judicial-Pessoa Física",
        "cidade": "Jaguaré",
        "uf": "ES",
        "latitude": -18.907006,
        "longitude": -40.0759,
        "empresa": "Oi S.a. - em Recuperacao Judicial",
        "cnpj": 76535764000143,
        "data-dados": "2025-01",
        "pf-ou-pj": "Pessoa Física",
        "info-tecnologia": [
            {
                "tecnologia": "ADSL1",
                "tipo-de-Produto": "INTERNET",
                "meio-de-acesso": "Cabo Metálico",
                "quantidade-acesso": 1
            },
            {
                "tecnologia": "ADSL2",
                "tipo-de-Produto": "INTERNET",
                "meio-de-acesso": "Cabo Metálico",
                "quantidade-acesso": 3
            }
        ]
    },
    {
        "identifier": "76535764000143-Jerônimo Monteiro-ES-Oi S.a. - em Recuperacao Judicial-Pessoa Física",
        "cidade": "Jerônimo Monteiro",
        "uf": "ES",
        "latitude": -20.799359,
        "longitude": -41.394848,
        "empresa": "Oi S.a. - em Recuperacao Judicial",
        "cnpj": 76535764000143,
        "data-dados": "2025-01",
        "pf-ou-pj": "Pessoa Física",
        "info-tecnologia": [
            {
                "tecnologia": "ADSL1",
                "tipo-de-Produto": "INTERNET",
                "meio-de-acesso": "Cabo Metálico",
                "quantidade-acesso": 1
            },
            {
                "tecnologia": "ADSL2",
                "tipo-de-Produto": "INTERNET",
                "meio-de-acesso": "Cabo Metálico",
                "quantidade-acesso": 5
            }
        ]
    },
    {
        "identifier": "76535764000143-João Neiva-ES-Oi S.a. - em Recuperacao Judicial-Pessoa Física",
        "cidade": "João Neiva",
        "uf": "ES",
        "latitude": -19.757707,
        "longitude": -40.385951,
        "empresa": "Oi S.a. - em Recuperacao Judicial",
        "cnpj": 76535764000143,
        "data-dados": "2025-01",
        "pf-ou-pj": "Pessoa Física",
        "info-tecnologia": [
            {
                "tecnologia": "ADSL1",
                "tipo-de-Produto": "INTERNET",
                "meio-de-acesso": "Cabo Metálico",
                "quantidade-acesso": 1
            },
            {
                "tecnologia": "ADSL2",
                "tipo-de-Produto": "INTERNET",
                "meio-de-acesso": "Cabo Metálico",
                "quantidade-acesso": 1
            }
        ]
    },
    {
        "identifier": "76535764000143-Linhares-ES-Oi S.a. - em Recuperacao Judicial-Pessoa Física",
        "cidade": "Linhares",
        "uf": "ES",
        "latitude": -19.394642,
        "longitude": -40.064277,
        "empresa": "Oi S.a. - em Recuperacao Judicial",
        "cnpj": 76535764000143,
        "data-dados": "2025-01",
        "pf-ou-pj": "Pessoa Física",
        "info-tecnologia": [
            {
                "tecnologia": "ADSL1",
                "tipo-de-Produto": "INTERNET",
                "meio-de-acesso": "Cabo Metálico",
                "quantidade-acesso": 2
            },
            {
                "tecnologia": "ADSL2",
                "tipo-de-Produto": "INTERNET",
                "meio-de-acesso": "Cabo Metálico",
                "quantidade-acesso": 7
            }
        ]
    },
    {
        "identifier": "76535764000143-Mantenópolis-ES-Oi S.a. - em Recuperacao Judicial-Pessoa Física",
        "cidade": "Mantenópolis",
        "uf": "ES",
        "latitude": -18.859428,
        "longitude": -41.124005,
        "empresa": "Oi S.a. - em Recuperacao Judicial",
        "cnpj": 76535764000143,
        "data-dados": "2025-01",
        "pf-ou-pj": "Pessoa Física",
        "info-tecnologia": [
            {
                "tecnologia": "ADSL1",
                "tipo-de-Produto": "INTERNET",
                "meio-de-acesso": "Cabo Metálico",
                "quantidade-acesso": 1
            },
            {
                "tecnologia": "ADSL2",
                "tipo-de-Produto": "INTERNET",
                "meio-de-acesso": "Cabo Metálico",
                "quantidade-acesso": 2
            }
        ]
    },
    {
        "identifier": "76535764000143-Marataízes-ES-Oi S.a. - em Recuperacao Judicial-Pessoa Física",
        "cidade": "Marataízes",
        "uf": "ES",
        "latitude": -21.039813,
        "longitude": -40.838436,
        "empresa": "Oi S.a. - em Recuperacao Judicial",
        "cnpj": 76535764000143,
        "data-dados": "2025-01",
        "pf-ou-pj": "Pessoa Física",
        "info-tecnologia": [
            {
                "tecnologia": "ADSL1",
                "tipo-de-Produto": "INTERNET",
                "meio-de-acesso": "Cabo Metálico",
                "quantidade-acesso": 4
            },
            {
                "tecnologia": "ADSL2",
                "tipo-de-Produto": "INTERNET",
                "meio-de-acesso": "Cabo Metálico",
                "quantidade-acesso": 11
            }
        ]
    },
    {
        "identifier": "76535764000143-Marechal Floriano-ES-Oi S.a. - em Recuperacao Judicial-Pessoa Física",
        "cidade": "Marechal Floriano",
        "uf": "ES",
        "latitude": -20.415889,
        "longitude": -40.669998,
        "empresa": "Oi S.a. - em Recuperacao Judicial",
        "cnpj": 76535764000143,
        "data-dados": "2025-01",
        "pf-ou-pj": "Pessoa Física",
        "info-tecnologia": [
            {
                "tecnologia": "ADSL1",
                "tipo-de-Produto": "INTERNET",
                "meio-de-acesso": "Cabo Metálico",
                "quantidade-acesso": 1
            },
            {
                "tecnologia": "ADSL2",
                "tipo-de-Produto": "INTERNET",
                "meio-de-acesso": "Cabo Metálico",
                "quantidade-acesso": 11
            }
        ]
    },
    {
        "identifier": "76535764000143-Marilândia-ES-Oi S.a. - em Recuperacao Judicial-Pessoa Física",
        "cidade": "Marilândia",
        "uf": "ES",
        "latitude": -19.411358,
        "longitude": -40.545648,
        "empresa": "Oi S.a. - em Recuperacao Judicial",
        "cnpj": 76535764000143,
        "data-dados": "2025-01",
        "pf-ou-pj": "Pessoa Física",
        "info-tecnologia": [
            {
                "tecnologia": "ADSL1",
                "tipo-de-Produto": "INTERNET",
                "meio-de-acesso": "Cabo Metálico",
                "quantidade-acesso": 1
            }
        ]
    },
    {
        "identifier": "76535764000143-Montanha-ES-Oi S.a. - em Recuperacao Judicial-Pessoa Física",
        "cidade": "Montanha",
        "uf": "ES",
        "latitude": -18.130287,
        "longitude": -40.366781,
        "empresa": "Oi S.a. - em Recuperacao Judicial",
        "cnpj": 76535764000143,
        "data-dados": "2025-01",
        "pf-ou-pj": "Pessoa Física",
        "info-tecnologia": [
            {
                "tecnologia": "ADSL1",
                "tipo-de-Produto": "INTERNET",
                "meio-de-acesso": "Cabo Metálico",
                "quantidade-acesso": 5
            }
        ]
    },
    {
        "identifier": "76535764000143-Muniz Freire-ES-Oi S.a. - em Recuperacao Judicial-Pessoa Física",
        "cidade": "Muniz Freire",
        "uf": "ES",
        "latitude": -20.465187,
        "longitude": -41.41563,
        "empresa": "Oi S.a. - em Recuperacao Judicial",
        "cnpj": 76535764000143,
        "data-dados": "2025-01",
        "pf-ou-pj": "Pessoa Física",
        "info-tecnologia": [
            {
                "tecnologia": "ADSL2",
                "tipo-de-Produto": "INTERNET",
                "meio-de-acesso": "Cabo Metálico",
                "quantidade-acesso": 1
            }
        ]
    },
    {
        "identifier": "76535764000143-Muqui-ES-Oi S.a. - em Recuperacao Judicial-Pessoa Física",
        "cidade": "Muqui",
        "uf": "ES",
        "latitude": -20.950859,
        "longitude": -41.345994,
        "empresa": "Oi S.a. - em Recuperacao Judicial",
        "cnpj": 76535764000143,
        "data-dados": "2025-01",
        "pf-ou-pj": "Pessoa Física",
        "info-tecnologia": [
            {
                "tecnologia": "ADSL1",
                "tipo-de-Produto": "INTERNET",
                "meio-de-acesso": "Cabo Metálico",
                "quantidade-acesso": 1
            }
        ]
    },
    {
        "identifier": "76535764000143-Nova Venécia-ES-Oi S.a. - em Recuperacao Judicial-Pessoa Física",
        "cidade": "Nova Venécia",
        "uf": "ES",
        "latitude": -18.715017,
        "longitude": -40.405273,
        "empresa": "Oi S.a. - em Recuperacao Judicial",
        "cnpj": 76535764000143,
        "data-dados": "2025-01",
        "pf-ou-pj": "Pessoa Física",
        "info-tecnologia": [
            {
                "tecnologia": "ADSL1",
                "tipo-de-Produto": "INTERNET",
                "meio-de-acesso": "Cabo Metálico",
                "quantidade-acesso": 1
            },
            {
                "tecnologia": "FTTH",
                "tipo-de-Produto": "INTERNET",
                "meio-de-acesso": "Fibra",
                "quantidade-acesso": 4236
            }
        ]
    },
    {
        "identifier": "76535764000143-Pedro Canário-ES-Oi S.a. - em Recuperacao Judicial-Pessoa Física",
        "cidade": "Pedro Canário",
        "uf": "ES",
        "latitude": -18.300418,
        "longitude": -39.957365,
        "empresa": "Oi S.a. - em Recuperacao Judicial",
        "cnpj": 76535764000143,
        "data-dados": "2025-01",
        "pf-ou-pj": "Pessoa Física",
        "info-tecnologia": [
            {
                "tecnologia": "ADSL2",
                "tipo-de-Produto": "INTERNET",
                "meio-de-acesso": "Cabo Metálico",
                "quantidade-acesso": 4
            }
        ]
    },
    {
        "identifier": "76535764000143-Pinheiros-ES-Oi S.a. - em Recuperacao Judicial-Pessoa Física",
        "cidade": "Pinheiros",
        "uf": "ES",
        "latitude": -18.414068,
        "longitude": -40.217142,
        "empresa": "Oi S.a. - em Recuperacao Judicial",
        "cnpj": 76535764000143,
        "data-dados": "2025-01",
        "pf-ou-pj": "Pessoa Física",
        "info-tecnologia": [
            {
                "tecnologia": "ADSL1",
                "tipo-de-Produto": "INTERNET",
                "meio-de-acesso": "Cabo Metálico",
                "quantidade-acesso": 3
            },
            {
                "tecnologia": "ADSL2",
                "tipo-de-Produto": "INTERNET",
                "meio-de-acesso": "Cabo Metálico",
                "quantidade-acesso": 6
            }
        ]
    },
    {
        "identifier": "76535764000143-Piúma-ES-Oi S.a. - em Recuperacao Judicial-Pessoa Física",
        "cidade": "Piúma",
        "uf": "ES",
        "latitude": -20.833433,
        "longitude": -40.726813,
        "empresa": "Oi S.a. - em Recuperacao Judicial",
        "cnpj": 76535764000143,
        "data-dados": "2025-01",
        "pf-ou-pj": "Pessoa Física",
        "info-tecnologia": [
            {
                "tecnologia": "ADSL2",
                "tipo-de-Produto": "INTERNET",
                "meio-de-acesso": "Cabo Metálico",
                "quantidade-acesso": 5
            }
        ]
    },
    {
        "identifier": "76535764000143-Rio Bananal-ES-Oi S.a. - em Recuperacao Judicial-Pessoa Física",
        "cidade": "Rio Bananal",
        "uf": "ES",
        "latitude": -19.271889,
        "longitude": -40.336605,
        "empresa": "Oi S.a. - em Recuperacao Judicial",
        "cnpj": 76535764000143,
        "data-dados": "2025-01",
        "pf-ou-pj": "Pessoa Física",
        "info-tecnologia": [
            {
                "tecnologia": "ADSL1",
                "tipo-de-Produto": "INTERNET",
                "meio-de-acesso": "Cabo Metálico",
                "quantidade-acesso": 1
            }
        ]
    },
    {
        "identifier": "76535764000143-Rio Novo do Sul-ES-Oi S.a. - em Recuperacao Judicial-Pessoa Física",
        "cidade": "Rio Novo do Sul",
        "uf": "ES",
        "latitude": -20.855619,
        "longitude": -40.938761,
        "empresa": "Oi S.a. - em Recuperacao Judicial",
        "cnpj": 76535764000143,
        "data-dados": "2025-01",
        "pf-ou-pj": "Pessoa Física",
        "info-tecnologia": [
            {
                "tecnologia": "ADSL1",
                "tipo-de-Produto": "INTERNET",
                "meio-de-acesso": "Cabo Metálico",
                "quantidade-acesso": 2
            },
            {
                "tecnologia": "ADSL2",
                "tipo-de-Produto": "INTERNET",
                "meio-de-acesso": "Cabo Metálico",
                "quantidade-acesso": 3
            }
        ]
    },
    {
        "identifier": "76535764000143-Santa Maria de Jetibá-ES-Oi S.a. - em Recuperacao Judicial-Pessoa Física",
        "cidade": "Santa Maria de Jetibá",
        "uf": "ES",
        "latitude": -20.025296,
        "longitude": -40.743931,
        "empresa": "Oi S.a. - em Recuperacao Judicial",
        "cnpj": 76535764000143,
        "data-dados": "2025-01",
        "pf-ou-pj": "Pessoa Física",
        "info-tecnologia": [
            {
                "tecnologia": "ADSL1",
                "tipo-de-Produto": "INTERNET",
                "meio-de-acesso": "Cabo Metálico",
                "quantidade-acesso": 2
            }
        ]
    },
    {
        "identifier": "76535764000143-Santa Teresa-ES-Oi S.a. - em Recuperacao Judicial-Pessoa Física",
        "cidade": "Santa Teresa",
        "uf": "ES",
        "latitude": -19.936339,
        "longitude": -40.597945,
        "empresa": "Oi S.a. - em Recuperacao Judicial",
        "cnpj": 76535764000143,
        "data-dados": "2025-01",
        "pf-ou-pj": "Pessoa Física",
        "info-tecnologia": [
            {
                "tecnologia": "ADSL1",
                "tipo-de-Produto": "INTERNET",
                "meio-de-acesso": "Cabo Metálico",
                "quantidade-acesso": 1
            },
            {
                "tecnologia": "ADSL2",
                "tipo-de-Produto": "INTERNET",
                "meio-de-acesso": "Cabo Metálico",
                "quantidade-acesso": 2
            }
        ]
    },
    {
        "identifier": "76535764000143-Serra-ES-Oi S.a. - em Recuperacao Judicial-Pessoa Física",
        "cidade": "Serra",
        "uf": "ES",
        "latitude": -20.121032,
        "longitude": -40.307408,
        "empresa": "Oi S.a. - em Recuperacao Judicial",
        "cnpj": 76535764000143,
        "data-dados": "2025-01",
        "pf-ou-pj": "Pessoa Física",
        "info-tecnologia": [
            {
                "tecnologia": "ADSL1",
                "tipo-de-Produto": "INTERNET",
                "meio-de-acesso": "Cabo Metálico",
                "quantidade-acesso": 1
            },
            {
                "tecnologia": "ADSL2",
                "tipo-de-Produto": "INTERNET",
                "meio-de-acesso": "Cabo Metálico",
                "quantidade-acesso": 11
            },
            {
                "tecnologia": "ADSL2",
                "tipo-de-Produto": "INTERNET",
                "meio-de-acesso": "Fibra",
                "quantidade-acesso": 1
            },
            {
                "tecnologia": "FTTH",
                "tipo-de-Produto": "INTERNET",
                "meio-de-acesso": "Fibra",
                "quantidade-acesso": 35201
            }
        ]
    },
    {
        "identifier": "76535764000143-Sooretama-ES-Oi S.a. - em Recuperacao Judicial-Pessoa Física",
        "cidade": "Sooretama",
        "uf": "ES",
        "latitude": -19.189695,
        "longitude": -40.097351,
        "empresa": "Oi S.a. - em Recuperacao Judicial",
        "cnpj": 76535764000143,
        "data-dados": "2025-01",
        "pf-ou-pj": "Pessoa Física",
        "info-tecnologia": [
            {
                "tecnologia": "ADSL2",
                "tipo-de-Produto": "INTERNET",
                "meio-de-acesso": "Cabo Metálico",
                "quantidade-acesso": 1
            }
        ]
    },
    {
        "identifier": "76535764000143-São Domingos do Norte-ES-Oi S.a. - em Recuperacao Judicial-Pessoa Física",
        "cidade": "São Domingos do Norte",
        "uf": "ES",
        "latitude": -19.145213,
        "longitude": -40.62812,
        "empresa": "Oi S.a. - em Recuperacao Judicial",
        "cnpj": 76535764000143,
        "data-dados": "2025-01",
        "pf-ou-pj": "Pessoa Física",
        "info-tecnologia": [
            {
                "tecnologia": "ADSL1",
                "tipo-de-Produto": "INTERNET",
                "meio-de-acesso": "Cabo Metálico",
                "quantidade-acesso": 1
            }
        ]
    },
    {
        "identifier": "76535764000143-São Gabriel da Palha-ES-Oi S.a. - em Recuperacao Judicial-Pessoa Física",
        "cidade": "São Gabriel da Palha",
        "uf": "ES",
        "latitude": -19.01819,
        "longitude": -40.536487,
        "empresa": "Oi S.a. - em Recuperacao Judicial",
        "cnpj": 76535764000143,
        "data-dados": "2025-01",
        "pf-ou-pj": "Pessoa Física",
        "info-tecnologia": [
            {
                "tecnologia": "FTTH",
                "tipo-de-Produto": "INTERNET",
                "meio-de-acesso": "Fibra",
                "quantidade-acesso": 1791
            }
        ]
    },
    {
        "identifier": "76535764000143-São José do Calçado-ES-Oi S.a. - em Recuperacao Judicial-Pessoa Física",
        "cidade": "São José do Calçado",
        "uf": "ES",
        "latitude": -21.027442,
        "longitude": -41.663627,
        "empresa": "Oi S.a. - em Recuperacao Judicial",
        "cnpj": 76535764000143,
        "data-dados": "2025-01",
        "pf-ou-pj": "Pessoa Física",
        "info-tecnologia": [
            {
                "tecnologia": "ADSL1",
                "tipo-de-Produto": "INTERNET",
                "meio-de-acesso": "Cabo Metálico",
                "quantidade-acesso": 2
            },
            {
                "tecnologia": "ADSL2",
                "tipo-de-Produto": "INTERNET",
                "meio-de-acesso": "Cabo Metálico",
                "quantidade-acesso": 6
            }
        ]
    },
    {
        "identifier": "76535764000143-São Mateus-ES-Oi S.a. - em Recuperacao Judicial-Pessoa Física",
        "cidade": "São Mateus",
        "uf": "ES",
        "latitude": -18.721407,
        "longitude": -39.857935,
        "empresa": "Oi S.a. - em Recuperacao Judicial",
        "cnpj": 76535764000143,
        "data-dados": "2025-01",
        "pf-ou-pj": "Pessoa Física",
        "info-tecnologia": [
            {
                "tecnologia": "ADSL1",
                "tipo-de-Produto": "INTERNET",
                "meio-de-acesso": "Cabo Metálico",
                "quantidade-acesso": 1
            },
            {
                "tecnologia": "ADSL2",
                "tipo-de-Produto": "INTERNET",
                "meio-de-acesso": "Cabo Metálico",
                "quantidade-acesso": 8
            }
        ]
    },
    {
        "identifier": "76535764000143-Venda Nova do Imigrante-ES-Oi S.a. - em Recuperacao Judicial-Pessoa Física",
        "cidade": "Venda Nova do Imigrante",
        "uf": "ES",
        "latitude": -20.327017,
        "longitude": -41.135545,
        "empresa": "Oi S.a. - em Recuperacao Judicial",
        "cnpj": 76535764000143,
        "data-dados": "2025-01",
        "pf-ou-pj": "Pessoa Física",
        "info-tecnologia": [
            {
                "tecnologia": "ADSL1",
                "tipo-de-Produto": "INTERNET",
                "meio-de-acesso": "Cabo Metálico",
                "quantidade-acesso": 3
            },
            {
                "tecnologia": "ADSL2",
                "tipo-de-Produto": "INTERNET",
                "meio-de-acesso": "Cabo Metálico",
                "quantidade-acesso": 4
            }
        ]
    },
    {
        "identifier": "76535764000143-Viana-ES-Oi S.a. - em Recuperacao Judicial-Pessoa Física",
        "cidade": "Viana",
        "uf": "ES",
        "latitude": -20.382503,
        "longitude": -40.493292,
        "empresa": "Oi S.a. - em Recuperacao Judicial",
        "cnpj": 76535764000143,
        "data-dados": "2025-01",
        "pf-ou-pj": "Pessoa Física",
        "info-tecnologia": [
            {
                "tecnologia": "ADSL1",
                "tipo-de-Produto": "INTERNET",
                "meio-de-acesso": "Cabo Metálico",
                "quantidade-acesso": 1
            },
            {
                "tecnologia": "ADSL2",
                "tipo-de-Produto": "INTERNET",
                "meio-de-acesso": "Cabo Metálico",
                "quantidade-acesso": 3
            },
            {
                "tecnologia": "FTTH",
                "tipo-de-Produto": "INTERNET",
                "meio-de-acesso": "Fibra",
                "quantidade-acesso": 1580
            }
        ]
    },
    {
        "identifier": "76535764000143-Vila Velha-ES-Oi S.a. - em Recuperacao Judicial-Pessoa Física",
        "cidade": "Vila Velha",
        "uf": "ES",
        "latitude": -20.341705,
        "longitude": -40.287458,
        "empresa": "Oi S.a. - em Recuperacao Judicial",
        "cnpj": 76535764000143,
        "data-dados": "2025-01",
        "pf-ou-pj": "Pessoa Física",
        "info-tecnologia": [
            {
                "tecnologia": "ADSL1",
                "tipo-de-Produto": "INTERNET",
                "meio-de-acesso": "Cabo Metálico",
                "quantidade-acesso": 1
            },
            {
                "tecnologia": "ADSL2",
                "tipo-de-Produto": "INTERNET",
                "meio-de-acesso": "Cabo Metálico",
                "quantidade-acesso": 10
            },
            {
                "tecnologia": "FTTH",
                "tipo-de-Produto": "INTERNET",
                "meio-de-acesso": "Fibra",
                "quantidade-acesso": 14635
            }
        ]
    },
    {
        "identifier": "76535764000143-Vitória-ES-Oi S.a. - em Recuperacao Judicial-Pessoa Física",
        "cidade": "Vitória",
        "uf": "ES",
        "latitude": -20.315472,
        "longitude": -40.312806,
        "empresa": "Oi S.a. - em Recuperacao Judicial",
        "cnpj": 76535764000143,
        "data-dados": "2025-01",
        "pf-ou-pj": "Pessoa Física",
        "info-tecnologia": [
            {
                "tecnologia": "ADSL2",
                "tipo-de-Produto": "INTERNET",
                "meio-de-acesso": "Cabo Metálico",
                "quantidade-acesso": 3
            },
            {
                "tecnologia": "ADSL2",
                "tipo-de-Produto": "INTERNET",
                "meio-de-acesso": "Fibra",
                "quantidade-acesso": 2
            },
            {
                "tecnologia": "FTTH",
                "tipo-de-Produto": "INTERNET",
                "meio-de-acesso": "Fibra",
                "quantidade-acesso": 20775
            }
        ]
    },
    {
        "identifier": "76535764000143-Água Doce do Norte-ES-Oi S.a. - em Recuperacao Judicial-Pessoa Física",
        "cidade": "Água Doce do Norte",
        "uf": "ES",
        "latitude": -18.54822,
        "longitude": -40.985411,
        "empresa": "Oi S.a. - em Recuperacao Judicial",
        "cnpj": 76535764000143,
        "data-dados": "2025-01",
        "pf-ou-pj": "Pessoa Física",
        "info-tecnologia": [
            {
                "tecnologia": "ADSL1",
                "tipo-de-Produto": "INTERNET",
                "meio-de-acesso": "Cabo Metálico",
                "quantidade-acesso": 1
            },
            {
                "tecnologia": "ADSL2",
                "tipo-de-Produto": "INTERNET",
                "meio-de-acesso": "Cabo Metálico",
                "quantidade-acesso": 2
            }
        ]
    },
    {
        "identifier": "76535764000143-Águia Branca-ES-Oi S.a. - em Recuperacao Judicial-Pessoa Física",
        "cidade": "Águia Branca",
        "uf": "ES",
        "latitude": -18.984588,
        "longitude": -40.74369,
        "empresa": "Oi S.a. - em Recuperacao Judicial",
        "cnpj": 76535764000143,
        "data-dados": "2025-01",
        "pf-ou-pj": "Pessoa Física",
        "info-tecnologia": [
            {
                "tecnologia": "ADSL1",
                "tipo-de-Produto": "INTERNET",
                "meio-de-acesso": "Cabo Metálico",
                "quantidade-acesso": 2
            },
            {
                "tecnologia": "ADSL2",
                "tipo-de-Produto": "INTERNET",
                "meio-de-acesso": "Cabo Metálico",
                "quantidade-acesso": 3
            }
        ]
    }
]